{"props":{"pageProps":{"profile":{"isStatic":true,"website":"https://www.cyrusone.com","industry":"REIT—Specialty","search":["c","co","con","cone","cy","cyr","cyru","cyrus","cyruso","cyruson","cyrusone","cyrusone ","cyrusone i","cyrusone in","cyrusone inc","cyrusone inc."],"description":"CyrusOne (NASDAQ: CONE) is a premier global REIT specializing in design, construction and operation of more than 50 high-performance data centers worldwide. The Company provides mission-critical facilities that ensure the continued operation of IT infrastructure for approximately 1,000 customers, including approximately 200 Fortune 1000 companies. A leader in hybrid-cloud and multi-cloud deployments, CyrusOne offers colocation, hyperscale, and build-to-suit environments that help customers enhance the strategic connection of their essential data infrastructure and support achievement of sustainability goals. CyrusOne data centers offer world-class flexibility, enabling clients to modernize, simplify, and rapidly respond to changing demand. Combining exceptional financial strength with a broad global footprint, CyrusOne provides customers with long-term stability and strategic advantage at scale.","sector":"Real Estate","symbol":"CONE","ipoDate":"2013-01-16","currency":"USD","exchangeShort":"NASDAQ","name":"CyrusOne Inc."},"incomeStatement":[{"data":{"operatingIncome":39300000,"incomeTaxExpense":-4900000,"epsdiluted":0.2,"incomeBeforeTax":20400000,"sellingGeneralAndAdministrativeExpenses":116800000,"generalAndAdministrativeExpenses":101900000,"researchAndDevelopmentExpenses":0,"operatingIncomeRatio":0.032595172928589204,"weightedAverageShsOut":123800000,"sellingAndMarketingExpenses":14900000,"revenue":1205700000,"otherExpenses":499200000,"grossProfit":674600000,"netIncome":25300000,"costOfRevenue":531100000,"eps":0.2,"operatingExpenses":616000000,"grossProfitRatio":0.5595089989217882,"netIncomeRatio":0.020983660943850044,"weightedAverageShsOutDil":123900000,"totalOtherIncomeExpensesNet":-18900000},"period":"FY","year":"2021"},{"period":"FY","year":"2020","data":{"grossProfit":621900000,"costOfRevenue":411600000,"operatingIncomeRatio":0.03880019351717465,"operatingExpenses":567000000,"revenue":1033500000,"netIncome":41400000,"totalOtherIncomeExpensesNet":-2300000,"otherExpenses":449400000,"eps":0.35,"incomeBeforeTax":37800000,"netIncomeRatio":0.04005805515239477,"sellingAndMarketingExpenses":18300000,"operatingIncome":40100000,"generalAndAdministrativeExpenses":99300000,"sellingGeneralAndAdministrativeExpenses":117600000,"weightedAverageShsOutDil":118285714,"incomeTaxExpense":-3600000,"grossProfitRatio":0.6017416545718433,"weightedAverageShsOut":118285714,"epsdiluted":0.35,"researchAndDevelopmentExpenses":0}},{"data":{"grossProfit":597900000,"netIncomeRatio":0.042188933047997555,"totalOtherIncomeExpensesNet":-29300000,"incomeBeforeTax":37700000,"netIncome":41400000,"operatingExpenses":521400000,"costOfRevenue":383400000,"eps":0.36,"weightedAverageShsOutDil":115000000,"epsdiluted":0.36,"operatingIncomeRatio":0.06827677570569653,"sellingGeneralAndAdministrativeExpenses":103700000,"weightedAverageShsOut":115000000,"otherExpenses":417700000,"incomeTaxExpense":-3700000,"operatingIncome":67000000,"generalAndAdministrativeExpenses":83500000,"researchAndDevelopmentExpenses":0,"sellingAndMarketingExpenses":20200000,"grossProfitRatio":0.6092937939468053,"revenue":981300000},"year":"2019","period":"FY"},{"data":{"researchAndDevelopmentExpenses":0,"weightedAverageShsOutDil":108329314,"epsdiluted":0.011077,"revenue":821400000,"grossProfitRatio":0.6440224007791575,"incomeBeforeTax":1800000,"otherExpenses":334100000,"netIncomeRatio":0.0014609203798392988,"totalOtherIncomeExpensesNet":-87900000,"operatingIncomeRatio":0.10920379839298758,"eps":0.011077,"operatingIncome":89700000,"operatingExpenses":434300000,"weightedAverageShsOut":108329314,"sellingAndMarketingExpenses":19600000,"grossProfit":529000000,"netIncome":1200000,"costOfRevenue":292400000,"incomeTaxExpense":600000,"generalAndAdministrativeExpenses":80600000,"sellingGeneralAndAdministrativeExpenses":100200000},"year":"2018","period":"FY"},{"data":{"epsdiluted":-0.95,"researchAndDevelopmentExpenses":0,"operatingIncome":24100000,"netIncome":-83500000,"eps":-0.95,"sellingGeneralAndAdministrativeExpenses":84000000,"netIncomeRatio":-0.12425595238095238,"operatingIncomeRatio":0.035863095238095236,"revenue":672000000,"operatingExpenses":342900000,"grossProfitRatio":0.6501488095238095,"sellingAndMarketingExpenses":17000000,"grossProfit":436900000,"otherExpenses":258900000,"incomeBeforeTax":-80500000,"totalOtherIncomeExpensesNet":-104600000,"generalAndAdministrativeExpenses":67000000,"costOfRevenue":235100000,"incomeTaxExpense":3000000,"weightedAverageShsOutDil":88900000,"weightedAverageShsOut":88900000},"period":"FY","year":"2017"},{"period":"FY","year":"2016","data":{"generalAndAdministrativeExpenses":60700000,"operatingIncome":70500000,"otherExpenses":183900000,"grossProfit":341600000,"operatingExpenses":261500000,"eps":0.24,"sellingAndMarketingExpenses":16900000,"epsdiluted":0.24,"incomeBeforeTax":21700000,"incomeTaxExpense":1800000,"netIncomeRatio":0.03761103761103761,"revenue":529100000,"sellingGeneralAndAdministrativeExpenses":77600000,"operatingIncomeRatio":0.13324513324513323,"netIncome":19900000,"grossProfitRatio":0.6456246456246456,"costOfRevenue":187500000,"weightedAverageShsOutDil":82916667,"totalOtherIncomeExpensesNet":-48800000,"weightedAverageShsOut":82916667,"researchAndDevelopmentExpenses":0}},{"period":"FY","data":{"operatingExpenses":200200000,"sellingGeneralAndAdministrativeExpenses":58700000,"costOfRevenue":148700000,"eps":-0.3,"netIncomeRatio":-0.03856749311294766,"sellingAndMarketingExpenses":12100000,"operatingIncomeRatio":0.05709992486851991,"totalOtherIncomeExpensesNet":-41200000,"incomeBeforeTax":-18400000,"otherExpenses":141500000,"grossProfit":250600000,"weightedAverageShsOutDil":51333333,"researchAndDevelopmentExpenses":0,"grossProfitRatio":0.6275982970197846,"netIncome":-15400000,"generalAndAdministrativeExpenses":46600000,"operatingIncome":22800000,"epsdiluted":-0.3,"incomeTaxExpense":1800000,"revenue":399300000,"weightedAverageShsOut":51333333},"year":"2015"},{"year":"2014","period":"FY","data":{"costOfRevenue":124500000,"epsdiluted":-0.20180320477460173,"grossProfitRatio":0.6237533998186764,"otherExpenses":118000000,"weightedAverageShsOutDil":38651517,"netIncomeRatio":-0.02357207615593835,"operatingIncome":40000000,"netIncome":-7800000,"sellingGeneralAndAdministrativeExpenses":47400000,"researchAndDevelopmentExpenses":0,"weightedAverageShsOut":38651517,"operatingIncomeRatio":0.12088244182532487,"incomeTaxExpense":1400000,"operatingExpenses":165400000,"grossProfit":206400000,"eps":-0.20180320477460173,"sellingAndMarketingExpenses":12800000,"incomeBeforeTax":-13100000,"generalAndAdministrativeExpenses":34600000,"revenue":330900000,"totalOtherIncomeExpensesNet":-53100000}},{"data":{"operatingExpenses":133800000,"operatingIncome":11600000,"sellingAndMarketingExpenses":10600000,"weightedAverageShsOutDil":20900000,"grossProfit":170300000,"totalOtherIncomeExpensesNet":-44900000,"revenue":263500000,"sellingGeneralAndAdministrativeExpenses":38600000,"weightedAverageShsOut":20900000,"netIncome":-5300000,"researchAndDevelopmentExpenses":0,"operatingIncomeRatio":0.04402277039848197,"eps":-0.28,"netIncomeRatio":-0.020113851992409868,"incomeTaxExpense":2300000,"otherExpenses":95200000,"epsdiluted":-0.28,"grossProfitRatio":0.6462998102466793,"generalAndAdministrativeExpenses":28000000,"costOfRevenue":93200000,"incomeBeforeTax":-33300000},"year":"2013","period":"FY"},{"year":"2012","data":{"operatingIncome":16300000,"operatingExpenses":106300000,"costOfRevenue":76000000,"eps":-1.045682,"weightedAverageShsOutDil":19413165,"netIncomeRatio":-0.09193840579710146,"grossProfit":144800000,"sellingGeneralAndAdministrativeExpenses":32900000,"epsdiluted":-1.045682,"researchAndDevelopmentExpenses":0,"revenue":220800000,"generalAndAdministrativeExpenses":23200000,"sellingAndMarketingExpenses":9700000,"netIncome":-20300000,"totalOtherIncomeExpensesNet":-41800000,"incomeBeforeTax":-25500000,"operatingIncomeRatio":0.07382246376811594,"incomeTaxExpense":-5100000,"grossProfitRatio":0.6557971014492754,"weightedAverageShsOut":19413165,"otherExpenses":73400000},"period":"FY"},{"period":"FY","data":{"operatingExpenses":79400000,"netIncomeRatio":0.00825536598789213,"grossProfitRatio":0.6796917996697853,"netIncome":1500000,"epsdiluted":0.07726715350124516,"generalAndAdministrativeExpenses":14800000,"incomeBeforeTax":3700000,"incomeTaxExpense":2200000,"operatingIncome":38000000,"costOfRevenue":58200000,"grossProfit":123500000,"operatingIncomeRatio":0.20913593835993396,"eps":0.07726715350124516,"sellingGeneralAndAdministrativeExpenses":23900000,"revenue":181700000,"totalOtherIncomeExpensesNet":-34300000,"otherExpenses":55500000,"sellingAndMarketingExpenses":9100000,"weightedAverageShsOut":19413165,"researchAndDevelopmentExpenses":0,"weightedAverageShsOutDil":19413165},"year":"2011"},{"year":"2010","data":{"netIncome":3500000,"generalAndAdministrativeExpenses":10600000,"costOfRevenue":43900000,"revenue":127500000,"eps":0.18029,"researchAndDevelopmentExpenses":0,"totalOtherIncomeExpensesNet":-11500000,"weightedAverageShsOutDil":19413165,"operatingIncomeRatio":0.1396078431372549,"weightedAverageShsOut":19413165,"netIncomeRatio":0.027450980392156862,"sellingGeneralAndAdministrativeExpenses":17400000,"grossProfit":83600000,"incomeBeforeTax":6300000,"operatingExpenses":53600000,"operatingIncome":17800000,"incomeTaxExpense":2700000,"grossProfitRatio":0.6556862745098039,"epsdiluted":0.18029,"otherExpenses":36200000,"sellingAndMarketingExpenses":6800000},"period":"FY"},{"year":"2009","period":"FY","data":{"otherExpenses":18000000,"netIncome":6100000,"netIncomeRatio":0.08232118758434548,"epsdiluted":0.31422,"generalAndAdministrativeExpenses":5700000,"costOfRevenue":31000000,"incomeBeforeTax":10000000,"sellingAndMarketingExpenses":5100000,"sellingGeneralAndAdministrativeExpenses":10800000,"revenue":74100000,"weightedAverageShsOutDil":19413165,"eps":0.31422,"researchAndDevelopmentExpenses":0,"operatingIncomeRatio":0.1767881241565452,"operatingExpenses":28800000,"grossProfit":43100000,"grossProfitRatio":0.581646423751687,"incomeTaxExpense":3900000,"totalOtherIncomeExpensesNet":-3100000,"weightedAverageShsOut":19413165,"operatingIncome":13100000}},{"data":{"totalOtherIncomeExpensesNet":-5200000,"grossProfitRatio":0.5599874371859297,"epsdiluted":-0.06,"weightedAverageShsOut":116666667,"generalAndAdministrativeExpenses":31500000,"costOfRevenue":140100000,"sellingGeneralAndAdministrativeExpenses":35300000,"grossProfit":178300000,"otherExpenses":126600000,"operatingIncomeRatio":-0.005653266331658292,"sellingAndMarketingExpenses":3800000,"incomeBeforeTax":-7000000,"operatingExpenses":161900000,"netIncome":-7000000,"operatingIncome":-1800000,"eps":-0.06,"incomeTaxExpense":0,"netIncomeRatio":-0.02198492462311558,"revenue":318400000,"weightedAverageShsOutDil":127900000,"researchAndDevelopmentExpenses":0},"year":"2021","period":"Q4"},{"period":"Q3","data":{"otherExpenses":127500000,"sellingAndMarketingExpenses":3600000,"operatingIncome":8500000,"costOfRevenue":133400000,"epsdiluted":0.05,"totalOtherIncomeExpensesNet":-2800000,"weightedAverageShsOut":124200000,"revenue":304100000,"generalAndAdministrativeExpenses":30800000,"netIncome":6700000,"incomeTaxExpense":-1000000,"weightedAverageShsOutDil":124300000,"operatingExpenses":161900000,"netIncomeRatio":0.022032226241367973,"researchAndDevelopmentExpenses":0,"grossProfit":170700000,"incomeBeforeTax":5700000,"grossProfitRatio":0.5613285103584347,"sellingGeneralAndAdministrativeExpenses":34400000,"operatingIncomeRatio":0.027951331798750412,"eps":0.05},"year":"2021"},{"period":"Q2","year":"2021","data":{"researchAndDevelopmentExpenses":0,"grossProfitRatio":0.5720309205903021,"totalOtherIncomeExpensesNet":-13500000,"sellingGeneralAndAdministrativeExpenses":20300000,"incomeTaxExpense":-2300000,"generalAndAdministrativeExpenses":16600000,"operatingExpenses":144000000,"weightedAverageShsOut":123333333,"eps":0.06,"epsdiluted":0.06,"costOfRevenue":121800000,"grossProfit":162800000,"operatingIncomeRatio":0.06535488404778636,"incomeBeforeTax":5100000,"weightedAverageShsOutDil":123333333,"netIncomeRatio":0.02600140548137737,"sellingAndMarketingExpenses":3700000,"netIncome":7400000,"operatingIncome":18600000,"otherExpenses":123700000,"revenue":284600000}},{"year":"2021","data":{"netIncomeRatio":0.06095110515740121,"epsdiluted":0.15,"totalOtherIncomeExpensesNet":2600000,"grossProfitRatio":0.5452109845947756,"netIncome":18200000,"weightedAverageShsOutDil":121333333,"incomeTaxExpense":-1600000,"operatingExpenses":148200000,"researchAndDevelopmentExpenses":0,"revenue":298600000,"weightedAverageShsOut":121333333,"sellingAndMarketingExpenses":3800000,"eps":0.15,"sellingGeneralAndAdministrativeExpenses":26800000,"otherExpenses":121400000,"incomeBeforeTax":16600000,"operatingIncomeRatio":0.04688546550569324,"generalAndAdministrativeExpenses":23000000,"grossProfit":162800000,"operatingIncome":14000000,"costOfRevenue":135800000},"period":"Q1"},{"data":{"weightedAverageShsOutDil":126666667,"grossProfit":158100000,"sellingGeneralAndAdministrativeExpenses":27700000,"sellingAndMarketingExpenses":5300000,"incomeTaxExpense":700000,"netIncomeRatio":0.07078986587183309,"epsdiluted":0.15,"eps":0.15,"totalOtherIncomeExpensesNet":9300000,"costOfRevenue":110300000,"operatingExpenses":146200000,"incomeBeforeTax":19700000,"weightedAverageShsOut":126666667,"generalAndAdministrativeExpenses":22400000,"operatingIncome":10400000,"grossProfitRatio":0.5890461997019374,"revenue":268400000,"researchAndDevelopmentExpenses":0,"operatingIncomeRatio":0.038748137108792845,"netIncome":19000000,"otherExpenses":118500000},"period":"Q4","year":"2020"},{"period":"Q3","year":"2020","data":{"grossProfitRatio":0.582572298325723,"otherExpenses":113100000,"operatingIncomeRatio":-0.01750380517503805,"eps":-0.32,"sellingGeneralAndAdministrativeExpenses":34200000,"incomeTaxExpense":-1900000,"revenue":262800000,"netIncomeRatio":-0.1419330289193303,"costOfRevenue":109700000,"incomeBeforeTax":-39200000,"researchAndDevelopmentExpenses":0,"generalAndAdministrativeExpenses":29700000,"sellingAndMarketingExpenses":4500000,"operatingIncome":-4600000,"operatingExpenses":147300000,"netIncome":-37300000,"weightedAverageShsOut":118700000,"totalOtherIncomeExpensesNet":-34600000,"weightedAverageShsOutDil":118700000,"epsdiluted":-0.32,"grossProfit":153100000}},{"period":"Q2","data":{"weightedAverageShsOut":115384615,"incomeBeforeTax":43800000,"operatingIncomeRatio":0.08229329173166927,"otherExpenses":109700000,"weightedAverageShsOutDil":115700000,"eps":0.39,"sellingAndMarketingExpenses":3800000,"incomeTaxExpense":-1200000,"generalAndAdministrativeExpenses":20300000,"revenue":256400000,"epsdiluted":0.39,"grossProfitRatio":0.6138845553822153,"totalOtherIncomeExpensesNet":22700000,"netIncomeRatio":0.17550702028081122,"netIncome":45000000,"sellingGeneralAndAdministrativeExpenses":24100000,"operatingExpenses":133800000,"operatingIncome":21100000,"costOfRevenue":99000000,"researchAndDevelopmentExpenses":0,"grossProfit":157400000},"year":"2020"},{"year":"2020","data":{"grossProfitRatio":0.6234241561610411,"weightedAverageShsOut":114900000,"costOfRevenue":92600000,"eps":0.13,"incomeBeforeTax":13500000,"operatingIncome":13200000,"sellingGeneralAndAdministrativeExpenses":31600000,"grossProfit":153300000,"operatingExpenses":139700000,"netIncome":14700000,"researchAndDevelopmentExpenses":0,"generalAndAdministrativeExpenses":26900000,"revenue":245900000,"epsdiluted":0.13,"incomeTaxExpense":-1200000,"netIncomeRatio":0.05978039853599024,"otherExpenses":108100000,"totalOtherIncomeExpensesNet":300000,"operatingIncomeRatio":0.05368035786905246,"sellingAndMarketingExpenses":4700000,"weightedAverageShsOutDil":115100000},"period":"Q1"},{"period":"Q4","year":"2019","data":{"weightedAverageShsOut":113260870,"incomeBeforeTax":-52200000,"operatingExpenses":134500000,"weightedAverageShsOutDil":113260870,"grossProfitRatio":0.6305632138637258,"sellingGeneralAndAdministrativeExpenses":26400000,"eps":-0.46,"researchAndDevelopmentExpenses":0,"generalAndAdministrativeExpenses":21900000,"costOfRevenue":93800000,"incomeTaxExpense":-100000,"sellingAndMarketingExpenses":4500000,"netIncome":-52100000,"operatingIncome":22300000,"netIncomeRatio":-0.20519889720362347,"grossProfit":160100000,"revenue":253900000,"otherExpenses":108100000,"epsdiluted":-0.46,"operatingIncomeRatio":0.08782985427333596,"totalOtherIncomeExpensesNet":-74500000}},{"data":{"operatingIncomeRatio":0.05261060183339976,"sellingAndMarketingExpenses":5100000,"operatingIncome":13200000,"operatingExpenses":130300000,"otherExpenses":105400000,"totalOtherIncomeExpensesNet":-2600000,"revenue":250900000,"incomeTaxExpense":-2000000,"costOfRevenue":103000000,"generalAndAdministrativeExpenses":19800000,"researchAndDevelopmentExpenses":0,"epsdiluted":0.11,"netIncome":12600000,"grossProfitRatio":0.5894778796333201,"eps":0.11,"grossProfit":147900000,"weightedAverageShsOutDil":113500000,"sellingGeneralAndAdministrativeExpenses":24900000,"weightedAverageShsOut":113100000,"incomeBeforeTax":10600000,"netIncomeRatio":0.0502192108409725},"year":"2019","period":"Q3"},{"data":{"netIncomeRatio":-0.033797216699801194,"costOfRevenue":103300000,"revenue":251500000,"operatingExpenses":127100000,"epsdiluted":-0.08,"operatingIncomeRatio":0.07833001988071571,"generalAndAdministrativeExpenses":19700000,"incomeTaxExpense":-1400000,"researchAndDevelopmentExpenses":0,"grossProfitRatio":0.5892644135188867,"incomeBeforeTax":-9900000,"netIncome":-8500000,"operatingIncome":19700000,"sellingAndMarketingExpenses":5300000,"weightedAverageShsOutDil":113100000,"eps":-0.08,"weightedAverageShsOut":106250000,"grossProfit":148200000,"otherExpenses":102100000,"sellingGeneralAndAdministrativeExpenses":25000000,"totalOtherIncomeExpensesNet":-29600000},"year":"2019","period":"Q2"},{"period":"Q1","data":{"operatingIncome":11800000,"incomeBeforeTax":89200000,"otherExpenses":102100000,"researchAndDevelopmentExpenses":0,"costOfRevenue":83300000,"grossProfit":141700000,"sellingAndMarketingExpenses":5300000,"generalAndAdministrativeExpenses":22200000,"epsdiluted":0.82,"sellingGeneralAndAdministrativeExpenses":27500000,"totalOtherIncomeExpensesNet":77400000,"weightedAverageShsOutDil":108800000,"revenue":225000000,"grossProfitRatio":0.6297777777777778,"weightedAverageShsOut":108300000,"operatingIncomeRatio":0.052444444444444446,"netIncome":89400000,"operatingExpenses":129600000,"eps":0.82,"incomeTaxExpense":-200000,"netIncomeRatio":0.3973333333333333},"year":"2019"},{"data":{"researchAndDevelopmentExpenses":0,"revenue":221300000,"grossProfitRatio":0.6475372797107998,"sellingAndMarketingExpenses":5600000,"netIncome":-105800000,"incomeBeforeTax":-107200000,"totalOtherIncomeExpensesNet":-122000000,"eps":-1,"otherExpenses":97900000,"netIncomeRatio":-0.4780840488025305,"weightedAverageShsOutDil":106100000,"generalAndAdministrativeExpenses":23400000,"incomeTaxExpense":-1400000,"costOfRevenue":78000000,"operatingIncomeRatio":0.06687754179846363,"operatingIncome":14800000,"weightedAverageShsOut":105800000,"epsdiluted":-1,"operatingExpenses":126900000,"grossProfit":143300000,"sellingGeneralAndAdministrativeExpenses":29000000},"year":"2018","period":"Q4"},{"year":"2018","data":{"grossProfitRatio":0.6239109390125847,"totalOtherIncomeExpensesNet":-62400000,"operatingIncome":20200000,"operatingIncomeRatio":0.09777347531461762,"otherExpenses":84000000,"incomeBeforeTax":-42200000,"revenue":206600000,"costOfRevenue":77700000,"sellingAndMarketingExpenses":4300000,"netIncome":-42400000,"netIncomeRatio":-0.20522749273959343,"incomeTaxExpense":200000,"operatingExpenses":107600000,"sellingGeneralAndAdministrativeExpenses":23600000,"eps":-0.43,"weightedAverageShsOutDil":99500000,"generalAndAdministrativeExpenses":19300000,"epsdiluted":-0.43,"grossProfit":128900000,"researchAndDevelopmentExpenses":0,"weightedAverageShsOut":98604651},"period":"Q3"},{"period":"Q2","year":"2018","data":{"incomeBeforeTax":106900000,"operatingIncomeRatio":0.13712544438801422,"netIncomeRatio":0.5378364652107669,"researchAndDevelopmentExpenses":0,"netIncome":105900000,"costOfRevenue":68900000,"sellingAndMarketingExpenses":4400000,"sellingGeneralAndAdministrativeExpenses":23000000,"grossProfit":128000000,"weightedAverageShsOutDil":99400000,"epsdiluted":1.06,"otherExpenses":77600000,"incomeTaxExpense":1000000,"revenue":196900000,"operatingIncome":27000000,"eps":1.07,"grossProfitRatio":0.6500761808024378,"operatingExpenses":100600000,"generalAndAdministrativeExpenses":18600000,"totalOtherIncomeExpensesNet":79900000,"weightedAverageShsOut":98600000}},{"period":"Q1","year":"2018","data":{"otherExpenses":74600000,"revenue":196600000,"incomeBeforeTax":44300000,"grossProfit":128800000,"researchAndDevelopmentExpenses":0,"totalOtherIncomeExpensesNet":16600000,"generalAndAdministrativeExpenses":19300000,"sellingAndMarketingExpenses":5300000,"operatingExpenses":99200000,"grossProfitRatio":0.6551373346897253,"weightedAverageShsOut":96000000,"eps":0.45,"netIncome":43500000,"sellingGeneralAndAdministrativeExpenses":24600000,"costOfRevenue":67800000,"operatingIncome":27700000,"weightedAverageShsOutDil":96600000,"netIncomeRatio":0.22126144455747712,"incomeTaxExpense":800000,"epsdiluted":0.45,"operatingIncomeRatio":0.14089521871820956}},{"period":"Q4","data":{"grossProfit":120300000,"operatingIncome":23900000,"incomeBeforeTax":3800000,"operatingExpenses":91100000,"epsdiluted":0.029166666666666667,"costOfRevenue":60200000,"netIncomeRatio":0.01551246537396122,"otherExpenses":70800000,"revenue":180500000,"sellingGeneralAndAdministrativeExpenses":20300000,"weightedAverageShsOut":96000000,"grossProfitRatio":0.6664819944598338,"generalAndAdministrativeExpenses":16400000,"operatingIncomeRatio":0.13240997229916898,"weightedAverageShsOutDil":96000000,"researchAndDevelopmentExpenses":0,"totalOtherIncomeExpensesNet":-20100000,"incomeTaxExpense":1000000,"netIncome":2800000,"sellingAndMarketingExpenses":3900000,"eps":0.029166666666666667},"year":"2017"},{"data":{"operatingIncome":-36300000,"costOfRevenue":63000000,"generalAndAdministrativeExpenses":17500000,"netIncome":-55100000,"weightedAverageShsOutDil":90900000,"netIncomeRatio":-0.3143183114660582,"totalOtherIncomeExpensesNet":-17900000,"revenue":175300000,"grossProfitRatio":0.6406160867084997,"weightedAverageShsOut":90327869,"epsdiluted":-0.61,"sellingAndMarketingExpenses":3900000,"otherExpenses":68700000,"grossProfit":112300000,"researchAndDevelopmentExpenses":0,"eps":-0.61,"operatingIncomeRatio":-0.20707358813462637,"operatingExpenses":90100000,"incomeBeforeTax":-54200000,"incomeTaxExpense":900000,"sellingGeneralAndAdministrativeExpenses":21400000},"year":"2017","period":"Q3"},{"year":"2017","data":{"sellingGeneralAndAdministrativeExpenses":21600000,"revenue":166900000,"otherExpenses":63700000,"totalOtherIncomeExpensesNet":-16800000,"costOfRevenue":59600000,"weightedAverageShsOut":80000000,"operatingIncomeRatio":0.10005991611743559,"researchAndDevelopmentExpenses":0,"sellingAndMarketingExpenses":4300000,"incomeTaxExpense":700000,"operatingIncome":16700000,"grossProfit":107300000,"generalAndAdministrativeExpenses":17300000,"grossProfitRatio":0.6428999400838825,"operatingExpenses":85300000,"incomeBeforeTax":-100000,"epsdiluted":-0.01,"weightedAverageShsOutDil":80000000,"eps":-0.01,"netIncome":-800000,"netIncomeRatio":-0.004793289394847214},"period":"Q2"},{"period":"Q1","data":{"operatingIncomeRatio":0.13261888814467515,"revenue":149300000,"sellingGeneralAndAdministrativeExpenses":20700000,"netIncome":-30400000,"grossProfitRatio":0.6496985934360349,"operatingExpenses":76400000,"epsdiluted":-0.36,"costOfRevenue":52300000,"operatingIncome":19800000,"incomeTaxExpense":400000,"researchAndDevelopmentExpenses":0,"generalAndAdministrativeExpenses":15800000,"otherExpenses":55700000,"eps":-0.36,"sellingAndMarketingExpenses":4900000,"weightedAverageShsOutDil":84444444,"netIncomeRatio":-0.20361687876758205,"grossProfit":97000000,"totalOtherIncomeExpensesNet":-49800000,"weightedAverageShsOut":84444444,"incomeBeforeTax":-30000000},"year":"2017"},{"period":"Q4","data":{"netIncome":800000,"sellingGeneralAndAdministrativeExpenses":21900000,"weightedAverageShsOut":80000000,"researchAndDevelopmentExpenses":0,"eps":0.01,"totalOtherIncomeExpensesNet":-11400000,"operatingExpenses":71200000,"incomeBeforeTax":1300000,"otherExpenses":49300000,"grossProfitRatio":0.6521106259097526,"netIncomeRatio":0.005822416302765648,"sellingAndMarketingExpenses":4000000,"generalAndAdministrativeExpenses":17900000,"epsdiluted":0.01,"operatingIncomeRatio":0.09243085880640466,"weightedAverageShsOutDil":80000000,"grossProfit":89600000,"revenue":137400000,"incomeTaxExpense":500000,"costOfRevenue":47800000,"operatingIncome":12700000},"year":"2016"},{"period":"Q3","data":{"grossProfitRatio":0.6203059805285118,"revenue":143800000,"operatingExpenses":69200000,"researchAndDevelopmentExpenses":0,"sellingGeneralAndAdministrativeExpenses":18600000,"totalOtherIncomeExpensesNet":-13800000,"incomeTaxExpense":600000,"generalAndAdministrativeExpenses":13900000,"operatingIncomeRatio":0.13073713490959665,"epsdiluted":0.05,"otherExpenses":50600000,"weightedAverageShsOut":80600000,"incomeBeforeTax":5000000,"operatingIncome":18800000,"sellingAndMarketingExpenses":4700000,"netIncome":4400000,"grossProfit":89200000,"weightedAverageShsOutDil":81300000,"netIncomeRatio":0.030598052851182198,"eps":0.05,"costOfRevenue":54600000},"year":"2016"},{"period":"Q2","year":"2016","data":{"otherExpenses":44700000,"revenue":130100000,"costOfRevenue":44800000,"netIncome":9100000,"operatingExpenses":63800000,"totalOtherIncomeExpensesNet":-11500000,"researchAndDevelopmentExpenses":0,"incomeBeforeTax":9600000,"operatingIncome":21100000,"weightedAverageShsOut":78300000,"sellingGeneralAndAdministrativeExpenses":19100000,"grossProfitRatio":0.6556495003843198,"incomeTaxExpense":500000,"netIncomeRatio":0.06994619523443504,"sellingAndMarketingExpenses":4200000,"operatingIncomeRatio":0.16218293620292082,"epsdiluted":0.11,"eps":0.11,"grossProfit":85300000,"weightedAverageShsOutDil":79000000,"generalAndAdministrativeExpenses":14900000}},{"data":{"incomeTaxExpense":200000,"costOfRevenue":40300000,"operatingIncome":17900000,"weightedAverageShsOutDil":72800000,"operatingExpenses":57300000,"netIncomeRatio":0.04753820033955857,"sellingAndMarketingExpenses":4000000,"generalAndAdministrativeExpenses":14000000,"sellingGeneralAndAdministrativeExpenses":18000000,"incomeBeforeTax":5800000,"revenue":117800000,"epsdiluted":0.07,"grossProfitRatio":0.6578947368421053,"otherExpenses":39300000,"researchAndDevelopmentExpenses":0,"eps":0.07,"weightedAverageShsOut":72100000,"grossProfit":77500000,"operatingIncomeRatio":0.15195246179966043,"netIncome":5600000,"totalOtherIncomeExpensesNet":-12100000},"year":"2016","period":"Q1"},{"data":{"netIncome":-1000000,"sellingGeneralAndAdministrativeExpenses":18300000,"weightedAverageShsOutDil":72556334,"totalOtherIncomeExpensesNet":-12000000,"costOfRevenue":41400000,"grossProfit":71900000,"generalAndAdministrativeExpenses":15100000,"incomeBeforeTax":-900000,"researchAndDevelopmentExpenses":0,"operatingExpenses":58200000,"epsdiluted":-0.013782394242796226,"operatingIncomeRatio":0.09796999117387467,"eps":-0.013782394242796226,"netIncomeRatio":-0.0088261253309797,"sellingAndMarketingExpenses":3200000,"grossProfitRatio":0.6345984112974404,"otherExpenses":39900000,"revenue":113300000,"incomeTaxExpense":300000,"operatingIncome":11100000,"weightedAverageShsOut":72556334},"year":"2015","period":"Q4"},{"year":"2015","data":{"grossProfitRatio":0.6205035971223022,"costOfRevenue":42200000,"grossProfit":69000000,"operatingIncome":7500000,"operatingExpenses":54800000,"epsdiluted":-0.08,"generalAndAdministrativeExpenses":12500000,"sellingAndMarketingExpenses":3200000,"totalOtherIncomeExpensesNet":-12100000,"incomeTaxExpense":700000,"eps":-0.08,"researchAndDevelopmentExpenses":0,"incomeBeforeTax":-4600000,"sellingGeneralAndAdministrativeExpenses":15700000,"weightedAverageShsOut":57500000,"weightedAverageShsOutDil":57500000,"otherExpenses":39100000,"netIncomeRatio":-0.04136690647482014,"revenue":111200000,"netIncome":-4600000,"operatingIncomeRatio":0.06744604316546762},"period":"Q3"},{"period":"Q2","year":"2015","data":{"netIncomeRatio":-0.06172839506172839,"epsdiluted":-0.11,"operatingIncomeRatio":0.029180695847362513,"sellingAndMarketingExpenses":2800000,"incomeTaxExpense":400000,"revenue":89100000,"netIncome":-5500000,"sellingGeneralAndAdministrativeExpenses":12700000,"grossProfit":56300000,"operatingIncome":2600000,"incomeBeforeTax":-6100000,"researchAndDevelopmentExpenses":0,"otherExpenses":31400000,"costOfRevenue":32800000,"operatingExpenses":44100000,"generalAndAdministrativeExpenses":9900000,"weightedAverageShsOutDil":50000000,"totalOtherIncomeExpensesNet":-8700000,"weightedAverageShsOut":50000000,"eps":-0.11,"grossProfitRatio":0.6318742985409652}},{"period":"Q1","year":"2015","data":{"costOfRevenue":32300000,"netIncome":-4300000,"sellingGeneralAndAdministrativeExpenses":12000000,"operatingIncome":1600000,"generalAndAdministrativeExpenses":9100000,"researchAndDevelopmentExpenses":0,"epsdiluted":-0.12,"revenue":85700000,"weightedAverageShsOutDil":35833333,"sellingAndMarketingExpenses":2900000,"totalOtherIncomeExpensesNet":-8400000,"incomeBeforeTax":-6800000,"weightedAverageShsOut":35833333,"incomeTaxExpense":400000,"grossProfit":53400000,"operatingIncomeRatio":0.01866977829638273,"otherExpenses":31100000,"eps":-0.12,"operatingExpenses":43100000,"grossProfitRatio":0.6231038506417736,"netIncomeRatio":-0.050175029171528586}},{"period":"Q4","data":{"operatingIncomeRatio":0.12888377445339472,"grossProfit":54900000,"weightedAverageShsOutDil":36842105,"netIncome":-7000000,"eps":-0.19,"operatingExpenses":43600000,"netIncomeRatio":-0.0805523590333717,"incomeTaxExpense":300000,"otherExpenses":30600000,"grossProfitRatio":0.6317606444188723,"weightedAverageShsOut":36842105,"costOfRevenue":32000000,"revenue":86900000,"researchAndDevelopmentExpenses":0,"totalOtherIncomeExpensesNet":-22700000,"epsdiluted":-0.19,"incomeBeforeTax":-11500000,"sellingAndMarketingExpenses":3100000,"generalAndAdministrativeExpenses":9900000,"sellingGeneralAndAdministrativeExpenses":13000000,"operatingIncome":11200000},"year":"2014"},{"data":{"epsdiluted":0.002587,"grossProfit":51800000,"operatingIncomeRatio":0.11320754716981132,"generalAndAdministrativeExpenses":9000000,"incomeTaxExpense":400000,"incomeBeforeTax":600000,"operatingIncome":9600000,"sellingAndMarketingExpenses":3200000,"weightedAverageShsOut":38653771,"eps":0.002587,"netIncomeRatio":0.0011792452830188679,"weightedAverageShsOutDil":38653771,"netIncome":100000,"researchAndDevelopmentExpenses":0,"sellingGeneralAndAdministrativeExpenses":12200000,"revenue":84800000,"totalOtherIncomeExpensesNet":-9000000,"operatingExpenses":42200000,"costOfRevenue":33000000,"otherExpenses":30000000,"grossProfitRatio":0.6108490566037735},"year":"2014","period":"Q3"},{"period":"Q2","data":{"netIncomeRatio":-0.01346389228886169,"operatingIncome":7400000,"incomeBeforeTax":-3300000,"grossProfit":49900000,"incomeTaxExpense":300000,"operatingExpenses":41700000,"totalOtherIncomeExpensesNet":-10700000,"sellingGeneralAndAdministrativeExpenses":11900000,"epsdiluted":-0.02845447035120499,"sellingAndMarketingExpenses":3500000,"grossProfitRatio":0.6107711138310894,"operatingIncomeRatio":0.09057527539779682,"researchAndDevelopmentExpenses":0,"weightedAverageShsOut":38658249,"netIncome":-1100000,"revenue":81700000,"generalAndAdministrativeExpenses":8400000,"eps":-0.02845447035120499,"otherExpenses":29800000,"weightedAverageShsOutDil":38658249,"costOfRevenue":31800000},"year":"2014"},{"year":"2014","data":{"eps":0.008819,"epsdiluted":0.008819,"operatingIncome":11800000,"operatingIncomeRatio":0.15225806451612903,"netIncomeRatio":0.0025806451612903226,"totalOtherIncomeExpensesNet":-10700000,"otherExpenses":27600000,"grossProfitRatio":0.6425806451612903,"incomeTaxExpense":400000,"sellingGeneralAndAdministrativeExpenses":10300000,"revenue":77500000,"costOfRevenue":27700000,"generalAndAdministrativeExpenses":7300000,"sellingAndMarketingExpenses":3000000,"grossProfit":49800000,"weightedAverageShsOutDil":22679417,"operatingExpenses":37900000,"researchAndDevelopmentExpenses":0,"weightedAverageShsOut":22679417,"incomeBeforeTax":1100000,"netIncome":200000},"period":"Q1"},{"year":"2013","period":"Q4","data":{"sellingAndMarketingExpenses":2600000,"grossProfit":48000000,"sellingGeneralAndAdministrativeExpenses":9400000,"operatingExpenses":36000000,"grossProfitRatio":0.6639004149377593,"incomeBeforeTax":-2500000,"netIncome":-1300000,"revenue":72300000,"operatingIncome":9000000,"totalOtherIncomeExpensesNet":-11500000,"eps":-0.06,"weightedAverageShsOut":20900000,"costOfRevenue":24300000,"operatingIncomeRatio":0.12448132780082988,"epsdiluted":-0.06,"researchAndDevelopmentExpenses":0,"otherExpenses":26600000,"incomeTaxExpense":1100000,"netIncomeRatio":-0.017980636237897647,"generalAndAdministrativeExpenses":6800000,"weightedAverageShsOutDil":20900000}},{"period":"Q3","data":{"totalOtherIncomeExpensesNet":-10400000,"operatingIncome":8500000,"grossProfitRatio":0.6414814814814814,"epsdiluted":-0.05,"sellingGeneralAndAdministrativeExpenses":9500000,"weightedAverageShsOut":16000000,"grossProfit":43300000,"netIncomeRatio":-0.011851851851851851,"generalAndAdministrativeExpenses":7200000,"incomeBeforeTax":-1900000,"netIncome":-800000,"costOfRevenue":24200000,"weightedAverageShsOutDil":16000000,"researchAndDevelopmentExpenses":0,"revenue":67500000,"otherExpenses":23900000,"incomeTaxExpense":300000,"sellingAndMarketingExpenses":2300000,"operatingIncomeRatio":0.1259259259259259,"eps":-0.05,"operatingExpenses":33400000},"year":"2013"},{"period":"Q2","year":"2013","data":{"epsdiluted":-0.12,"sellingGeneralAndAdministrativeExpenses":10000000,"generalAndAdministrativeExpenses":7100000,"totalOtherIncomeExpensesNet":-12100000,"grossProfit":39000000,"incomeTaxExpense":300000,"grossProfitRatio":0.6132075471698113,"incomeBeforeTax":-6500000,"operatingIncome":5600000,"weightedAverageShsOutDil":19166667,"netIncome":-2300000,"operatingExpenses":33000000,"weightedAverageShsOut":19166667,"operatingIncomeRatio":0.0880503144654088,"researchAndDevelopmentExpenses":0,"netIncomeRatio":-0.036163522012578615,"sellingAndMarketingExpenses":2900000,"eps":-0.12,"revenue":63600000,"otherExpenses":23000000,"costOfRevenue":24600000}},{"period":"Q1","year":"2013","data":{"researchAndDevelopmentExpenses":0,"costOfRevenue":20100000,"grossProfitRatio":0.6655574043261231,"weightedAverageShsOutDil":18000000,"sellingAndMarketingExpenses":2800000,"otherExpenses":21700000,"generalAndAdministrativeExpenses":6900000,"netIncome":-900000,"operatingExpenses":31400000,"eps":-0.05,"incomeTaxExpense":600000,"operatingIncomeRatio":-0.1913477537437604,"epsdiluted":-0.05,"weightedAverageShsOut":18000000,"sellingGeneralAndAdministrativeExpenses":9700000,"revenue":60100000,"grossProfit":40000000,"operatingIncome":-11500000,"totalOtherIncomeExpensesNet":-10900000,"incomeBeforeTax":-22400000,"netIncomeRatio":-0.014975041597337771}},{"year":"2012","data":{"eps":-0.355429,"operatingIncomeRatio":0.056896551724137934,"weightedAverageShsOutDil":19413165,"grossProfit":37300000,"netIncome":-6900000,"operatingIncome":3300000,"incomeBeforeTax":-7300000,"netIncomeRatio":-0.11896551724137931,"grossProfitRatio":0.6431034482758621,"operatingExpenses":30100000,"sellingAndMarketingExpenses":3900000,"revenue":58000000,"generalAndAdministrativeExpenses":5700000,"epsdiluted":-0.355429,"researchAndDevelopmentExpenses":0,"otherExpenses":20500000,"sellingGeneralAndAdministrativeExpenses":9600000,"totalOtherIncomeExpensesNet":-10600000,"weightedAverageShsOut":19413165,"incomeTaxExpense":-400000,"costOfRevenue":20700000},"period":"Q1"},{"year":"2012","data":{"sellingAndMarketingExpenses":2100000,"costOfRevenue":20000000,"revenue":56700000,"researchAndDevelopmentExpenses":0,"operatingIncomeRatio":0.13580246913580246,"sellingGeneralAndAdministrativeExpenses":8300000,"operatingExpenses":27100000,"operatingIncome":7700000,"epsdiluted":-0.14423201986899098,"weightedAverageShsOut":19413165,"grossProfitRatio":0.6472663139329806,"incomeBeforeTax":-3600000,"weightedAverageShsOutDil":19413165,"netIncomeRatio":-0.04938271604938271,"eps":-0.14423201986899098,"netIncome":-2800000,"incomeTaxExpense":-700000,"generalAndAdministrativeExpenses":6200000,"grossProfit":36700000,"otherExpenses":18800000,"totalOtherIncomeExpensesNet":-11300000},"period":"Q3"},{"data":{"operatingExpenses":27400000,"grossProfit":35900000,"generalAndAdministrativeExpenses":6800000,"researchAndDevelopmentExpenses":0,"epsdiluted":-0.509963,"weightedAverageShsOut":19413165,"sellingGeneralAndAdministrativeExpenses":8500000,"operatingIncomeRatio":-0.08888888888888889,"costOfRevenue":18100000,"operatingIncome":-4800000,"totalOtherIncomeExpensesNet":-9700000,"revenue":54000000,"netIncomeRatio":-0.18333333333333332,"grossProfitRatio":0.6648148148148149,"eps":-0.509963,"sellingAndMarketingExpenses":1700000,"otherExpenses":18900000,"weightedAverageShsOutDil":19413165,"netIncome":-9900000,"incomeTaxExpense":-4600000,"incomeBeforeTax":-14500000},"year":"2012","period":"Q2"},{"year":"2012","period":"Q1","data":{"researchAndDevelopmentExpenses":0,"totalOtherIncomeExpensesNet":-10300000,"operatingIncomeRatio":0.19577735124760076,"netIncome":-700000,"grossProfit":34800000,"incomeBeforeTax":-100000,"generalAndAdministrativeExpenses":5200000,"weightedAverageShsOut":19413165,"netIncomeRatio":-0.013435700575815739,"eps":-0.036058,"grossProfitRatio":0.6679462571976967,"weightedAverageShsOutDil":19413165,"operatingIncome":10200000,"sellingGeneralAndAdministrativeExpenses":7000000,"sellingAndMarketingExpenses":1800000,"operatingExpenses":24600000,"otherExpenses":17600000,"revenue":52100000,"costOfRevenue":17300000,"incomeTaxExpense":600000,"epsdiluted":-0.036058}},{"period":"Q4","year":"2011","data":{"researchAndDevelopmentExpenses":0,"generalAndAdministrativeExpenses":4400000,"costOfRevenue":14900000,"weightedAverageShsOutDil":19413165,"totalOtherIncomeExpensesNet":-10200000,"weightedAverageShsOut":19413165,"netIncomeRatio":-0.00625,"grossProfitRatio":0.6895833333333333,"epsdiluted":-0.015453430700249031,"incomeBeforeTax":-200000,"operatingExpenses":21900000,"operatingIncome":10000000,"incomeTaxExpense":100000,"sellingAndMarketingExpenses":2000000,"sellingGeneralAndAdministrativeExpenses":6400000,"operatingIncomeRatio":0.20833333333333334,"grossProfit":33100000,"revenue":48000000,"netIncome":-300000,"otherExpenses":15500000,"eps":-0.015453430700249031}},{"period":"Q3","year":"2011","data":{"epsdiluted":0.025756,"operatingExpenses":20700000,"revenue":46500000,"costOfRevenue":15500000,"eps":0.025756,"operatingIncome":9100000,"generalAndAdministrativeExpenses":4300000,"incomeTaxExpense":700000,"netIncomeRatio":0.010752688172043012,"netIncome":500000,"weightedAverageShsOut":19413165,"sellingGeneralAndAdministrativeExpenses":6900000,"grossProfit":31000000,"weightedAverageShsOutDil":19413165,"sellingAndMarketingExpenses":2600000,"otherExpenses":13800000,"operatingIncomeRatio":0.1956989247311828,"researchAndDevelopmentExpenses":0,"incomeBeforeTax":1200000,"grossProfitRatio":0.6666666666666666,"totalOtherIncomeExpensesNet":-7900000}},{"year":"2011","period":"Q2","data":{"incomeBeforeTax":2500000,"costOfRevenue":14100000,"grossProfit":30400000,"operatingIncome":10600000,"netIncomeRatio":0.03146067415730337,"incomeTaxExpense":1100000,"revenue":44500000,"sellingAndMarketingExpenses":2400000,"grossProfitRatio":0.6831460674157304,"netIncome":1400000,"sellingGeneralAndAdministrativeExpenses":5200000,"eps":0.072116,"totalOtherIncomeExpensesNet":-8100000,"weightedAverageShsOutDil":19413165,"weightedAverageShsOut":19413165,"operatingExpenses":19400000,"generalAndAdministrativeExpenses":2800000,"operatingIncomeRatio":0.23820224719101124,"researchAndDevelopmentExpenses":0,"otherExpenses":14200000,"epsdiluted":0.072116}},{"period":"Q1","year":"2011","data":{"generalAndAdministrativeExpenses":3400000,"sellingAndMarketingExpenses":2100000,"epsdiluted":-0.005151,"eps":-0.005151,"incomeTaxExpense":300000,"totalOtherIncomeExpensesNet":-8100000,"sellingGeneralAndAdministrativeExpenses":5500000,"weightedAverageShsOutDil":19413165,"revenue":42700000,"operatingExpenses":18500000,"costOfRevenue":13700000,"operatingIncomeRatio":0.19437939110070257,"operatingIncome":8300000,"researchAndDevelopmentExpenses":0,"incomeBeforeTax":200000,"otherExpenses":13000000,"netIncomeRatio":-0.00234192037470726,"grossProfit":29000000,"weightedAverageShsOut":19413165,"netIncome":-100000,"grossProfitRatio":0.6791569086651054}}]},"__N_SSG":true},"page":"/quote/[symbol]/income-statement","query":{"symbol":"CONE"},"buildId":"Njk4sJo_1dBWR55wHuASm","isFallback":false,"gsp":true,"scriptLoader":[]}