{"props":{"pageProps":{"profile":{"industry":"Software—Infrastructure","description":"VMware, Inc. provides software solutions in the areas of modern applications, cloud management and infrastructure, networking, security, and digital workspaces in the United States and internationally. It offers VMware multi-cloud solutions, including VMware vSphere, a data center infrastructure that provides the fundamental compute layer; vSAN and VxRail, which offers holistic data storage and protection options to applications running on vSphere; and vRealize Cloud Management solutions that manages hybrid and multi-cloud environments running in virtual machines and containers, as well as VMware Cloud Foundation, a cloud platform that combines its vSphere, vSAN, and NSX with vRealize Cloud Management into an integrated stack and delivers enterprise-ready cloud infrastructure for private and public clouds. The company also provides networking solutions, such as VMware NSX, NSX Distributed and Gateway Firewalls, NSX Network Detection and Response Engine, NSX Advanced Load Balancer, Tanzu Service Mesh, and VMware SASE; security solutions consisting of VMware Carbon Black Endpoint, Workload, and Container; and digital workspace solutions comprising Workspace ONE Unified Endpoint Management, Access, Intelligent Hub, and Horizon. In addition, it offers application modernization solutions, such as Tanzu Application and Operations Platform, Tanzu Application Service Platform, Tanzu Observability, Tanzu Community Edition, and Tanzu Labs; and cloud management solutions, including vRealize Cloud Management, vCloud Suite, and CloudHealth by VMware Suite. The company sells its products through distributors, resellers, system vendors, and systems integrators. VMware, Inc. has a strategic alliance with Amazon Web Services to build and deliver an integrated hybrid solution. The company was incorporated in 1998 and is headquartered in Palo Alto, California.","website":"https://www.vmware.com","currency":"USD","isStatic":true,"name":"VMware, Inc.","sector":"Technology","search":["v","vm","vmw","vmwa","vmwar","vmware","vmware,","vmware, ","vmware, i","vmware, in","vmware, inc","vmware, inc."],"exchangeShort":"NYSE","symbol":"VMW","ipoDate":"2007-08-14"},"incomeStatement":[{"data":{"epsdiluted":4.3,"sellingAndMarketingExpenses":4067000000,"eps":4.33,"operatingIncome":2387000000,"operatingIncomeRatio":0.18574430005447046,"incomeTaxExpense":265000000,"netIncome":1820000000,"costOfRevenue":2385000000,"revenue":12851000000,"generalAndAdministrativeExpenses":1068000000,"weightedAverageShsOutDil":423240000,"weightedAverageShsOut":419841000,"grossProfit":10466000000,"sellingGeneralAndAdministrativeExpenses":5135000000,"researchAndDevelopmentExpenses":3057000000,"grossProfitRatio":0.8144113298575987,"netIncomeRatio":0.14162321998288072,"totalOtherIncomeExpensesNet":-302000000,"incomeBeforeTax":2085000000,"operatingExpenses":8192000000,"otherExpenses":0},"period":"FY","year":"2022"},{"data":{"eps":4.9,"sellingGeneralAndAdministrativeExpenses":4478000000,"weightedAverageShsOutDil":423240000,"epsdiluted":4.86,"revenue":11767000000,"generalAndAdministrativeExpenses":767000000,"totalOtherIncomeExpensesNet":-6000000,"incomeBeforeTax":2382000000,"grossProfit":9724000000,"grossProfitRatio":0.826378856123056,"netIncomeRatio":0.1748958953004164,"operatingIncome":2388000000,"weightedAverageShsOut":419841000,"researchAndDevelopmentExpenses":2816000000,"incomeTaxExpense":324000000,"netIncome":2058000000,"operatingIncomeRatio":0.20294042661680972,"otherExpenses":0,"sellingAndMarketingExpenses":3711000000,"costOfRevenue":2043000000,"operatingExpenses":7294000000},"year":"2021","period":"FY"},{"year":"2020","period":"FY","data":{"generalAndAdministrativeExpenses":1293000000,"epsdiluted":15.08,"weightedAverageShsOutDil":425235000,"operatingIncome":1441000000,"sellingAndMarketingExpenses":3677000000,"totalOtherIncomeExpensesNet":-3000000,"costOfRevenue":1799000000,"otherExpenses":0,"operatingExpenses":7492000000,"weightedAverageShsOut":417058000,"grossProfitRatio":0.8335954120802886,"grossProfit":9012000000,"operatingIncomeRatio":0.13329016742207012,"incomeBeforeTax":1438000000,"researchAndDevelopmentExpenses":2522000000,"netIncome":6412000000,"incomeTaxExpense":-4918000000,"eps":15.37,"revenue":10811000000,"sellingGeneralAndAdministrativeExpenses":4970000000,"netIncomeRatio":0.5930996207566368}},{"year":"2019","data":{"operatingIncome":2050000000,"netIncome":2422000000,"weightedAverageShsOut":407766000,"epsdiluted":5.85,"incomeBeforeTax":2883000000,"incomeTaxExpense":461000000,"grossProfit":7716000000,"weightedAverageShsOutDil":414267000,"revenue":8974000000,"operatingExpenses":5666000000,"sellingGeneralAndAdministrativeExpenses":3421000000,"grossProfitRatio":0.8598172498328505,"sellingAndMarketingExpenses":2918000000,"generalAndAdministrativeExpenses":503000000,"researchAndDevelopmentExpenses":1975000000,"otherExpenses":270000000,"operatingIncomeRatio":0.2284377089369289,"totalOtherIncomeExpensesNet":833000000,"netIncomeRatio":0.2698907956318253,"costOfRevenue":1258000000,"eps":5.94},"period":"FY"},{"data":{"operatingIncome":1689000000,"sellingGeneralAndAdministrativeExpenses":3247000000,"totalOtherIncomeExpensesNet":112000000,"otherExpenses":0,"sellingAndMarketingExpenses":2593000000,"costOfRevenue":1141000000,"netIncome":570000000,"operatingExpenses":5002000000,"epsdiluted":1.38,"weightedAverageShsOutDil":413368000,"netIncomeRatio":0.07195152739207271,"revenue":7922000000,"incomeBeforeTax":1801000000,"grossProfit":6781000000,"generalAndAdministrativeExpenses":654000000,"operatingIncomeRatio":0.21320373643019438,"incomeTaxExpense":1231000000,"grossProfitRatio":0.8559707144660439,"eps":1.4,"weightedAverageShsOut":406738000,"researchAndDevelopmentExpenses":1755000000},"year":"2018","period":"FY"},{"data":{"revenue":7093000000,"totalOtherIncomeExpensesNet":34000000,"sellingAndMarketingExpenses":2357000000,"researchAndDevelopmentExpenses":1503000000,"otherExpenses":0,"incomeTaxExpense":287000000,"weightedAverageShsOut":420520000,"operatingIncome":1439000000,"sellingGeneralAndAdministrativeExpenses":3046000000,"operatingExpenses":4549000000,"netIncomeRatio":0.16720710559706753,"operatingIncomeRatio":0.20287607500352461,"incomeBeforeTax":1473000000,"eps":2.82,"netIncome":1186000000,"epsdiluted":2.78,"generalAndAdministrativeExpenses":689000000,"grossProfitRatio":0.8515437755533625,"costOfRevenue":1053000000,"grossProfit":6040000000,"weightedAverageShsOutDil":423994000},"period":"FY","year":"2016"},{"data":{"revenue":6571000000,"sellingGeneralAndAdministrativeExpenses":3033000000,"operatingIncomeRatio":0.18216405417744636,"generalAndAdministrativeExpenses":766000000,"incomeTaxExpense":216000000,"sellingAndMarketingExpenses":2267000000,"operatingExpenses":4333000000,"eps":2.35,"epsdiluted":2.34,"operatingIncome":1197000000,"weightedAverageShsOutDil":426547000,"researchAndDevelopmentExpenses":1300000000,"grossProfitRatio":0.8450768528382285,"incomeBeforeTax":1213000000,"grossProfit":5553000000,"totalOtherIncomeExpensesNet":16000000,"netIncome":997000000,"netIncomeRatio":0.1517272865621671,"costOfRevenue":1018000000,"weightedAverageShsOut":424003000,"otherExpenses":0},"period":"FY","year":"2015"},{"data":{"incomeTaxExpense":162000000,"weightedAverageShsOut":430355000,"incomeBeforeTax":1048000000,"otherExpenses":0,"epsdiluted":2.04,"eps":2.06,"revenue":6035000000,"generalAndAdministrativeExpenses":695000000,"netIncomeRatio":0.1468102734051367,"weightedAverageShsOutDil":434513000,"costOfRevenue":917000000,"sellingAndMarketingExpenses":2141000000,"netIncome":886000000,"grossProfit":5118000000,"researchAndDevelopmentExpenses":1239000000,"operatingExpenses":4075000000,"grossProfitRatio":0.8480530240265121,"totalOtherIncomeExpensesNet":21000000,"sellingGeneralAndAdministrativeExpenses":2836000000,"operatingIncome":1027000000,"operatingIncomeRatio":0.17017398508699255},"year":"2014","period":"FY"},{"data":{"incomeBeforeTax":1147000000,"revenue":5207000000,"epsdiluted":2.34,"operatingExpenses":3316000000,"costOfRevenue":730000000,"weightedAverageShsOut":429093000,"incomeTaxExpense":133000000,"weightedAverageShsOutDil":433415000,"generalAndAdministrativeExpenses":419000000,"researchAndDevelopmentExpenses":1082000000,"grossProfitRatio":0.8598041098521222,"eps":2.36,"netIncomeRatio":0.19473785289033993,"netIncome":1014000000,"grossProfit":4477000000,"operatingIncomeRatio":0.20990973689264453,"otherExpenses":0,"operatingIncome":1093000000,"sellingGeneralAndAdministrativeExpenses":2234000000,"sellingAndMarketingExpenses":1815000000,"totalOtherIncomeExpensesNet":54000000},"period":"FY","year":"2013"},{"period":"FY","year":"2012","data":{"revenue":4605047000,"operatingIncome":871943000,"incomeBeforeTax":893114000,"weightedAverageShsOutDil":433974000,"epsdiluted":1.72,"grossProfitRatio":0.8433625107409327,"operatingExpenses":3011781000,"otherExpenses":0,"netIncomeRatio":0.16193146345737622,"operatingIncomeRatio":0.1893450816028588,"sellingGeneralAndAdministrativeExpenses":2012567000,"netIncome":745702000,"totalOtherIncomeExpensesNet":21171000,"incomeTaxExpense":147412000,"eps":1.75,"generalAndAdministrativeExpenses":367718000,"costOfRevenue":721323000,"weightedAverageShsOut":426658000,"researchAndDevelopmentExpenses":999214000,"sellingAndMarketingExpenses":1644849000,"grossProfit":3883724000}},{"data":{"grossProfit":3145109000,"revenue":3767096000,"operatingExpenses":2409938000,"operatingIncome":735171000,"sellingAndMarketingExpenses":1334346000,"incomeTaxExpense":70477000,"netIncome":723936000,"costOfRevenue":621987000,"weightedAverageShsOut":421188000,"incomeBeforeTax":794413000,"sellingGeneralAndAdministrativeExpenses":1634887000,"researchAndDevelopmentExpenses":775051000,"operatingIncomeRatio":0.19515589727471772,"netIncomeRatio":0.19217349385309002,"grossProfitRatio":0.834889527636142,"generalAndAdministrativeExpenses":300541000,"weightedAverageShsOutDil":431750000,"totalOtherIncomeExpensesNet":59242000,"eps":1.72,"epsdiluted":1.68,"otherExpenses":0},"period":"FY","year":"2011"},{"period":"FY","data":{"sellingAndMarketingExpenses":1013281000,"grossProfitRatio":0.8272118538096407,"totalOtherIncomeExpensesNet":-11618000,"netIncomeRatio":0.12509488710315841,"incomeBeforeTax":416375000,"eps":0.87,"costOfRevenue":493715000,"revenue":2857343000,"netIncome":357439000,"sellingGeneralAndAdministrativeExpenses":1282667000,"grossProfit":2363628000,"otherExpenses":0,"epsdiluted":0.84,"researchAndDevelopmentExpenses":652968000,"weightedAverageShsOutDil":423446000,"generalAndAdministrativeExpenses":269386000,"weightedAverageShsOut":409805000,"operatingIncomeRatio":0.14978705741662796,"operatingExpenses":1935635000,"operatingIncome":427993000,"incomeTaxExpense":58936000},"year":"2010"},{"period":"FY","data":{"operatingIncomeRatio":0.10835070459208958,"incomeTaxExpense":26351000,"revenue":2023937000,"otherExpenses":0,"weightedAverageShsOutDil":399776000,"grossProfit":1664209000,"costOfRevenue":359728000,"netIncomeRatio":0.09738346598733064,"sellingGeneralAndAdministrativeExpenses":948362000,"grossProfitRatio":0.8222632423835327,"operatingExpenses":1444914000,"netIncome":197098000,"operatingIncome":219295000,"sellingAndMarketingExpenses":736383000,"researchAndDevelopmentExpenses":496552000,"incomeBeforeTax":223449000,"weightedAverageShsOut":394269000,"totalOtherIncomeExpensesNet":4154000,"generalAndAdministrativeExpenses":211979000,"epsdiluted":0.49,"eps":0.5},"year":"2009"},{"data":{"sellingGeneralAndAdministrativeExpenses":835193000,"revenue":1881027000,"otherExpenses":0,"epsdiluted":0.73,"weightedAverageShsOutDil":397185000,"generalAndAdministrativeExpenses":181110000,"incomeBeforeTax":319285000,"grossProfit":1576922000,"netIncomeRatio":0.154241805141553,"incomeTaxExpense":29152000,"totalOtherIncomeExpensesNet":6760000,"eps":0.75,"costOfRevenue":304105000,"grossProfitRatio":0.8383303376293908,"operatingExpenses":1264397000,"operatingIncome":312525000,"sellingAndMarketingExpenses":654083000,"weightedAverageShsOut":385068000,"netIncome":290133000,"operatingIncomeRatio":0.1661459404888925,"researchAndDevelopmentExpenses":429204000},"year":"2008","period":"FY"},{"period":"FY","year":"2007","data":{"eps":0.62,"grossProfit":1107137000,"sellingGeneralAndAdministrativeExpenses":585855000,"netIncomeRatio":0.16453099272822447,"incomeTaxExpense":22341000,"revenue":1325811000,"sellingAndMarketingExpenses":0,"generalAndAdministrativeExpenses":0,"operatingIncomeRatio":0.17750720125266722,"grossProfitRatio":0.8350639721649616,"weightedAverageShsOut":350493000,"incomeBeforeTax":240478000,"operatingExpenses":871796000,"researchAndDevelopmentExpenses":285941000,"netIncome":218137000,"otherExpenses":0,"totalOtherIncomeExpensesNet":5137000,"operatingIncome":235341000,"costOfRevenue":218674000,"epsdiluted":0.61,"weightedAverageShsOutDil":359189000}},{"period":"FY","data":{"operatingExpenses":456183000,"sellingGeneralAndAdministrativeExpenses":307929000,"weightedAverageShsOutDil":332500000,"weightedAverageShsOut":332500000,"otherExpenses":0,"incomeBeforeTax":122547000,"sellingAndMarketingExpenses":0,"eps":0.26,"netIncome":85890000,"grossProfitRatio":0.8247175751238806,"incomeTaxExpense":36832000,"totalOtherIncomeExpensesNet":1908000,"researchAndDevelopmentExpenses":148254000,"costOfRevenue":123382000,"grossProfit":580522000,"epsdiluted":0.26,"netIncomeRatio":0.12201947992908124,"operatingIncomeRatio":0.17138558667090967,"revenue":703904000,"generalAndAdministrativeExpenses":0,"operatingIncome":120639000},"year":"2006"},{"period":"FY","year":"2005","data":{"sellingGeneralAndAdministrativeExpenses":155726000,"totalOtherIncomeExpensesNet":1745000,"eps":0.2,"incomeTaxExpense":28565000,"researchAndDevelopmentExpenses":72561000,"netIncomeRatio":0.1725122328030299,"weightedAverageShsOutDil":332500000,"sellingAndMarketingExpenses":0,"generalAndAdministrativeExpenses":0,"grossProfit":321882000,"weightedAverageShsOut":332500000,"operatingIncomeRatio":0.24180130931036442,"epsdiluted":0.2,"operatingIncome":93595000,"otherExpenses":0,"grossProfitRatio":0.8315774244718064,"operatingExpenses":228287000,"revenue":387074000,"costOfRevenue":65192000,"incomeBeforeTax":95340000,"netIncome":66775000}},{"year":"2004","data":{"generalAndAdministrativeExpenses":0,"grossProfit":0,"incomeTaxExpense":0,"netIncome":16781000,"totalOtherIncomeExpensesNet":0,"operatingExpenses":0,"otherExpenses":0,"netIncomeRatio":0.07671103878293624,"operatingIncomeRatio":1,"weightedAverageShsOutDil":332500000,"grossProfitRatio":0,"sellingAndMarketingExpenses":0,"incomeBeforeTax":0,"researchAndDevelopmentExpenses":0,"sellingGeneralAndAdministrativeExpenses":0,"eps":0.05,"weightedAverageShsOut":332500000,"revenue":218756000,"costOfRevenue":0,"operatingIncome":218756000,"epsdiluted":0.05},"period":"FY"},{"data":{"researchAndDevelopmentExpenses":1514000000,"weightedAverageShsOutDil":422976000,"generalAndAdministrativeExpenses":496000000,"operatingIncome":784000000,"epsdiluted":1.39,"incomeTaxExpense":137000000,"sellingAndMarketingExpenses":2033000000,"weightedAverageShsOut":420089000,"netIncomeRatio":5.080402010050252,"incomeBeforeTax":1148000000,"sellingGeneralAndAdministrativeExpenses":2529000000,"costOfRevenue":1252000000,"otherExpenses":0,"grossProfitRatio":-5.291457286432161,"operatingIncomeRatio":3.9396984924623117,"netIncome":1011000000,"grossProfit":-1053000000,"revenue":199000000,"eps":1.39,"totalOtherIncomeExpensesNet":364000000,"operatingExpenses":4043000000},"year":"2022","period":"Q4"},{"data":{"grossProfit":2614000000,"sellingGeneralAndAdministrativeExpenses":1327000000,"weightedAverageShsOutDil":421763000,"operatingIncomeRatio":0.16279799247176913,"incomeTaxExpense":59000000,"otherExpenses":0,"costOfRevenue":574000000,"netIncome":398000000,"operatingIncome":519000000,"revenue":3188000000,"generalAndAdministrativeExpenses":316000000,"incomeBeforeTax":457000000,"sellingAndMarketingExpenses":1011000000,"totalOtherIncomeExpensesNet":-62000000,"researchAndDevelopmentExpenses":768000000,"operatingExpenses":2095000000,"netIncomeRatio":0.12484316185696362,"grossProfitRatio":0.8199498117942283,"epsdiluted":0.94,"eps":0.95,"weightedAverageShsOut":419456000},"year":"2022","period":"Q3"},{"data":{"netIncome":411000000,"generalAndAdministrativeExpenses":256000000,"incomeTaxExpense":69000000,"epsdiluted":0.97,"otherExpenses":0,"sellingGeneralAndAdministrativeExpenses":1279000000,"grossProfit":2579000000,"eps":0.98,"weightedAverageShsOutDil":422802000,"totalOtherIncomeExpensesNet":-45000000,"researchAndDevelopmentExpenses":775000000,"netIncomeRatio":0.13097514340344169,"sellingAndMarketingExpenses":1023000000,"revenue":3138000000,"incomeBeforeTax":480000000,"weightedAverageShsOut":419355000,"operatingIncome":525000000,"costOfRevenue":559000000,"grossProfitRatio":0.8218610579987253,"operatingExpenses":2054000000,"operatingIncomeRatio":0.16730401529636713},"year":"2022","period":"Q2"},{"year":"2022","data":{"researchAndDevelopmentExpenses":708000000,"netIncomeRatio":0.14195056780227122,"operatingExpenses":1903000000,"netIncome":425000000,"costOfRevenue":531000000,"operatingIncome":559000000,"grossProfitRatio":0.8226452905811623,"eps":1.01,"epsdiluted":1.01,"sellingGeneralAndAdministrativeExpenses":1195000000,"incomeTaxExpense":61000000,"generalAndAdministrativeExpenses":236000000,"sellingAndMarketingExpenses":959000000,"weightedAverageShsOutDil":422038000,"totalOtherIncomeExpensesNet":-73000000,"weightedAverageShsOut":419116000,"operatingIncomeRatio":0.18670674682698732,"otherExpenses":0,"incomeBeforeTax":486000000,"revenue":2994000000,"grossProfit":2463000000},"period":"Q1"},{"year":"2021","period":"Q4","data":{"incomeBeforeTax":965000000,"epsdiluted":1.87,"costOfRevenue":555000000,"sellingAndMarketingExpenses":984000000,"grossProfitRatio":0.831511839708561,"otherExpenses":0,"netIncome":791000000,"weightedAverageShsOutDil":422813000,"operatingExpenses":1736000000,"weightedAverageShsOut":420090000,"revenue":3294000000,"eps":1.88,"grossProfit":2739000000,"operatingIncome":1008000000,"researchAndDevelopmentExpenses":758000000,"totalOtherIncomeExpensesNet":-43000000,"incomeTaxExpense":174000000,"operatingIncomeRatio":0.30601092896174864,"generalAndAdministrativeExpenses":-6000000,"sellingGeneralAndAdministrativeExpenses":978000000,"netIncomeRatio":0.24013357619914996}},{"year":"2021","data":{"incomeBeforeTax":554000000,"sellingGeneralAndAdministrativeExpenses":250000000,"weightedAverageShsOutDil":423400000,"operatingExpenses":1876000000,"eps":1.03,"researchAndDevelopmentExpenses":714000000,"sellingAndMarketingExpenses":912000000,"operatingIncome":428000000,"netIncomeRatio":0.15153631284916202,"operatingIncomeRatio":0.1494413407821229,"otherExpenses":912000000,"grossProfit":2319000000,"incomeTaxExpense":120000000,"costOfRevenue":545000000,"grossProfitRatio":0.8097067039106145,"generalAndAdministrativeExpenses":-662000000,"totalOtherIncomeExpensesNet":126000000,"weightedAverageShsOut":420857000,"netIncome":434000000,"revenue":2864000000,"epsdiluted":1.02},"period":"Q3"},{"data":{"operatingExpenses":1853000000,"epsdiluted":1.06,"sellingAndMarketingExpenses":897000000,"totalOtherIncomeExpensesNet":-39000000,"weightedAverageShsOutDil":423050000,"researchAndDevelopmentExpenses":679000000,"revenue":2875000000,"weightedAverageShsOut":420031000,"operatingIncomeRatio":0.1857391304347826,"eps":1.06,"generalAndAdministrativeExpenses":277000000,"grossProfitRatio":0.8302608695652174,"costOfRevenue":488000000,"sellingGeneralAndAdministrativeExpenses":1174000000,"grossProfit":2387000000,"incomeTaxExpense":48000000,"incomeBeforeTax":495000000,"operatingIncome":534000000,"otherExpenses":0,"netIncome":447000000,"netIncomeRatio":0.1554782608695652},"period":"Q2","year":"2021"},{"year":"2021","data":{"grossProfitRatio":0.8229700073152889,"researchAndDevelopmentExpenses":665000000,"generalAndAdministrativeExpenses":146000000,"operatingIncomeRatio":0.1528895391367959,"operatingExpenses":1832000000,"operatingIncome":418000000,"totalOtherIncomeExpensesNet":-50000000,"netIncomeRatio":0.14118507681053402,"grossProfit":2250000000,"epsdiluted":0.92,"sellingAndMarketingExpenses":917000000,"netIncome":386000000,"weightedAverageShsOut":418383000,"otherExpenses":104000000,"incomeTaxExpense":-18000000,"incomeBeforeTax":368000000,"sellingGeneralAndAdministrativeExpenses":1063000000,"eps":0.92,"revenue":2734000000,"weightedAverageShsOutDil":421513000,"costOfRevenue":484000000},"period":"Q1"},{"period":"Q4","year":"2020","data":{"sellingAndMarketingExpenses":1275000000,"totalOtherIncomeExpensesNet":161000000,"operatingIncome":72000000,"weightedAverageShsOutDil":424007000,"netIncome":361000000,"revenue":3073000000,"grossProfitRatio":0.7712333224861698,"epsdiluted":0.76,"costOfRevenue":703000000,"weightedAverageShsOut":417225000,"eps":0.77,"otherExpenses":0,"generalAndAdministrativeExpenses":668000000,"operatingIncomeRatio":0.02342987308818744,"operatingExpenses":2796000000,"researchAndDevelopmentExpenses":853000000,"grossProfit":2370000000,"sellingGeneralAndAdministrativeExpenses":1943000000,"incomeTaxExpense":-72000000,"incomeBeforeTax":233000000,"netIncomeRatio":0.1174747803449398}},{"period":"Q3","year":"2020","data":{"generalAndAdministrativeExpenses":159000000,"epsdiluted":1.5,"totalOtherIncomeExpensesNet":235000000,"costOfRevenue":378000000,"sellingAndMarketingExpenses":827000000,"revenue":2456000000,"researchAndDevelopmentExpenses":582000000,"netIncome":621000000,"incomeBeforeTax":666000000,"grossProfit":2078000000,"otherExpenses":79000000,"weightedAverageShsOutDil":414054000,"operatingIncomeRatio":0.1754885993485342,"incomeTaxExpense":45000000,"operatingIncome":431000000,"weightedAverageShsOut":409165000,"sellingGeneralAndAdministrativeExpenses":986000000,"grossProfitRatio":0.8460912052117264,"netIncomeRatio":0.2528501628664495,"operatingExpenses":1647000000,"eps":1.52}},{"year":"2020","data":{"sellingAndMarketingExpenses":796000000,"revenue":2439000000,"netIncomeRatio":2.1742517425174253,"operatingIncomeRatio":0.21443214432144322,"sellingGeneralAndAdministrativeExpenses":1067000000,"incomeTaxExpense":-4798000000,"otherExpenses":44000000,"weightedAverageShsOutDil":416288000,"grossProfit":1998000000,"netIncome":5303000000,"operatingExpenses":1725000000,"operatingIncome":523000000,"researchAndDevelopmentExpenses":614000000,"generalAndAdministrativeExpenses":271000000,"grossProfitRatio":0.8191881918819188,"eps":12.02,"incomeBeforeTax":487000000,"costOfRevenue":441000000,"totalOtherIncomeExpensesNet":-36000000,"weightedAverageShsOut":409761000,"epsdiluted":11.83},"period":"Q2"},{"period":"Q1","year":"2020","data":{"revenue":2266000000,"costOfRevenue":429000000,"researchAndDevelopmentExpenses":590000000,"operatingIncome":415000000,"incomeBeforeTax":351000000,"sellingGeneralAndAdministrativeExpenses":989000000,"weightedAverageShsOutDil":418387000,"otherExpenses":88000000,"sellingAndMarketingExpenses":779000000,"generalAndAdministrativeExpenses":210000000,"grossProfitRatio":0.8106796116504854,"netIncomeRatio":0.1676963812886143,"incomeTaxExpense":-14000000,"epsdiluted":0.9082500173284542,"netIncome":380000000,"grossProfit":1837000000,"eps":0.9258943408363263,"totalOtherIncomeExpensesNet":-64000000,"operatingIncomeRatio":0.18314210061782876,"operatingExpenses":1667000000,"weightedAverageShsOut":410414000}},{"data":{"operatingIncome":664000000,"incomeTaxExpense":89000000,"operatingExpenses":1585000000,"incomeBeforeTax":591000000,"researchAndDevelopmentExpenses":542000000,"grossProfitRatio":0.8680046314164416,"costOfRevenue":342000000,"weightedAverageShsOutDil":416451000,"epsdiluted":1.21,"sellingGeneralAndAdministrativeExpenses":975000000,"sellingAndMarketingExpenses":808000000,"weightedAverageShsOut":410277000,"otherExpenses":68000000,"netIncomeRatio":0.1937475878039367,"grossProfit":2249000000,"netIncome":502000000,"totalOtherIncomeExpensesNet":-73000000,"eps":1.22,"revenue":2591000000,"operatingIncomeRatio":0.25627170976456964,"generalAndAdministrativeExpenses":167000000},"year":"2019","period":"Q4"},{"period":"Q3","data":{"grossProfit":1885000000,"revenue":2200000000,"operatingIncome":495000000,"operatingExpenses":1390000000,"incomeTaxExpense":11000000,"sellingAndMarketingExpenses":707000000,"operatingIncomeRatio":0.225,"otherExpenses":70000000,"grossProfitRatio":0.8568181818181818,"eps":0.82,"epsdiluted":0.81,"incomeBeforeTax":345000000,"generalAndAdministrativeExpenses":114000000,"costOfRevenue":315000000,"netIncomeRatio":0.15181818181818182,"sellingGeneralAndAdministrativeExpenses":821000000,"researchAndDevelopmentExpenses":499000000,"totalOtherIncomeExpensesNet":-150000000,"weightedAverageShsOut":408708000,"netIncome":334000000,"weightedAverageShsOutDil":414477000},"year":"2019"},{"data":{"totalOtherIncomeExpensesNet":263000000,"incomeBeforeTax":772000000,"netIncome":644000000,"operatingIncomeRatio":0.23413063477460902,"operatingExpenses":1360000000,"grossProfitRatio":0.859705611775529,"costOfRevenue":305000000,"epsdiluted":1.56,"weightedAverageShsOutDil":413286000,"researchAndDevelopmentExpenses":481000000,"otherExpenses":62000000,"revenue":2174000000,"generalAndAdministrativeExpenses":120000000,"sellingAndMarketingExpenses":697000000,"incomeTaxExpense":128000000,"operatingIncome":509000000,"eps":1.58,"netIncomeRatio":0.29622815087396503,"grossProfit":1869000000,"weightedAverageShsOut":407112000,"sellingGeneralAndAdministrativeExpenses":817000000},"period":"Q2","year":"2019"},{"period":"Q1","data":{"epsdiluted":2.29,"sellingGeneralAndAdministrativeExpenses":808000000,"weightedAverageShsOut":404968000,"eps":2.33,"sellingAndMarketingExpenses":706000000,"researchAndDevelopmentExpenses":453000000,"generalAndAdministrativeExpenses":102000000,"operatingExpenses":1330000000,"costOfRevenue":296000000,"grossProfitRatio":0.852589641434263,"operatingIncome":382000000,"grossProfit":1712000000,"revenue":2008000000,"otherExpenses":69000000,"incomeTaxExpense":233000000,"operatingIncomeRatio":0.1902390438247012,"weightedAverageShsOutDil":410932000,"netIncomeRatio":0.46912350597609564,"totalOtherIncomeExpensesNet":793000000,"incomeBeforeTax":1175000000,"netIncome":942000000},"year":"2019"},{"year":"2018","period":"Q4","data":{"operatingExpenses":1356000000,"sellingGeneralAndAdministrativeExpenses":899000000,"totalOtherIncomeExpensesNet":20000000,"revenue":2310000000,"netIncome":-439000000,"weightedAverageShsOut":403383000,"costOfRevenue":304000000,"incomeTaxExpense":1107000000,"netIncomeRatio":-0.19004329004329004,"researchAndDevelopmentExpenses":457000000,"weightedAverageShsOutDil":403383000,"generalAndAdministrativeExpenses":168000000,"epsdiluted":-1.09,"eps":-1.09,"grossProfit":2006000000,"sellingAndMarketingExpenses":731000000,"operatingIncomeRatio":0.2805194805194805,"grossProfitRatio":0.8683982683982684,"incomeBeforeTax":668000000,"operatingIncome":648000000,"otherExpenses":0}},{"period":"Q3","year":"2018","data":{"netIncome":443000000,"sellingAndMarketingExpenses":607000000,"epsdiluted":1.07,"operatingIncomeRatio":0.2353238866396761,"incomeBeforeTax":468000000,"generalAndAdministrativeExpenses":175000000,"netIncomeRatio":0.2241902834008097,"eps":1.09,"otherExpenses":0,"operatingIncome":465000000,"grossProfit":1698000000,"weightedAverageShsOutDil":413013000,"grossProfitRatio":0.8593117408906883,"totalOtherIncomeExpensesNet":3000000,"costOfRevenue":278000000,"incomeTaxExpense":25000000,"operatingExpenses":1231000000,"researchAndDevelopmentExpenses":449000000,"sellingGeneralAndAdministrativeExpenses":782000000,"weightedAverageShsOut":406733000,"revenue":1976000000}},{"period":"Q2","year":"2018","data":{"weightedAverageShsOutDil":412768000,"revenue":1900000000,"netIncome":334000000,"generalAndAdministrativeExpenses":160000000,"grossProfitRatio":0.8578947368421053,"sellingGeneralAndAdministrativeExpenses":828000000,"incomeBeforeTax":407000000,"otherExpenses":0,"netIncomeRatio":0.17578947368421052,"operatingIncome":338000000,"operatingIncomeRatio":0.17789473684210527,"costOfRevenue":270000000,"epsdiluted":0.81,"researchAndDevelopmentExpenses":428000000,"totalOtherIncomeExpensesNet":69000000,"weightedAverageShsOut":408399000,"eps":0.82,"incomeTaxExpense":73000000,"grossProfit":1630000000,"sellingAndMarketingExpenses":668000000,"operatingExpenses":1256000000}},{"period":"Q4","year":"2018","data":{"netIncome":0,"incomeBeforeTax":0,"epsdiluted":0.56,"grossProfitRatio":0,"totalOtherIncomeExpensesNet":0,"operatingIncomeRatio":0,"sellingAndMarketingExpenses":0,"generalAndAdministrativeExpenses":0,"revenue":0,"otherExpenses":0,"weightedAverageShsOut":408431000,"operatingExpenses":0,"researchAndDevelopmentExpenses":0,"netIncomeRatio":0,"sellingGeneralAndAdministrativeExpenses":737000000,"eps":0.57,"costOfRevenue":0,"operatingIncome":238000000,"incomeTaxExpense":0,"weightedAverageShsOutDil":414018000,"grossProfit":0}},{"period":"Q3","data":{"incomeTaxExpense":108000000,"otherExpenses":0,"grossProfit":1759000000,"netIncome":441000000,"researchAndDevelopmentExpenses":394000000,"netIncomeRatio":0.21692080668962124,"costOfRevenue":274000000,"weightedAverageShsOut":412118000,"epsdiluted":1.04,"operatingIncome":543000000,"incomeBeforeTax":549000000,"eps":1.07,"weightedAverageShsOutDil":416512000,"revenue":2033000000,"generalAndAdministrativeExpenses":173000000,"sellingAndMarketingExpenses":649000000,"grossProfitRatio":0.8652238071815052,"operatingIncomeRatio":0.2670929660600098,"sellingGeneralAndAdministrativeExpenses":822000000,"totalOtherIncomeExpensesNet":6000000,"operatingExpenses":1216000000},"year":"2016"},{"data":{"costOfRevenue":266000000,"weightedAverageShsOut":421704000,"incomeTaxExpense":68000000,"incomeBeforeTax":387000000,"netIncome":319000000,"generalAndAdministrativeExpenses":178000000,"totalOtherIncomeExpensesNet":6000000,"researchAndDevelopmentExpenses":389000000,"epsdiluted":0.75,"otherExpenses":0,"sellingGeneralAndAdministrativeExpenses":742000000,"netIncomeRatio":0.17941507311586052,"operatingExpenses":1131000000,"revenue":1778000000,"grossProfit":1512000000,"eps":0.76,"operatingIncomeRatio":0.21428571428571427,"weightedAverageShsOutDil":425008000,"operatingIncome":381000000,"sellingAndMarketingExpenses":564000000,"grossProfitRatio":0.8503937007874016},"period":"Q2","year":"2016"},{"period":"Q1","year":"2016","data":{"weightedAverageShsOutDil":427102000,"otherExpenses":0,"incomeTaxExpense":72000000,"sellingGeneralAndAdministrativeExpenses":747000000,"researchAndDevelopmentExpenses":363000000,"grossProfit":1432000000,"netIncomeRatio":0.15652687536916715,"generalAndAdministrativeExpenses":167000000,"revenue":1693000000,"sellingAndMarketingExpenses":580000000,"netIncome":265000000,"eps":0.62,"totalOtherIncomeExpensesNet":14000000,"operatingIncomeRatio":0.19078558771411694,"operatingIncome":323000000,"weightedAverageShsOut":425107000,"epsdiluted":0.62,"grossProfitRatio":0.8458357944477259,"costOfRevenue":261000000,"incomeBeforeTax":337000000,"operatingExpenses":1110000000}},{"period":"Q4","year":"2016","data":{"weightedAverageShsOutDil":424180000,"totalOtherIncomeExpensesNet":8000000,"netIncomeRatio":0.1013215859030837,"sellingGeneralAndAdministrativeExpenses":737000000,"incomeBeforeTax":200000000,"otherExpenses":0,"grossProfitRatio":0.842039018250472,"netIncome":161000000,"grossProfit":1338000000,"eps":0.38,"incomeTaxExpense":39000000,"revenue":1589000000,"weightedAverageShsOut":423230000,"operatingExpenses":1093000000,"operatingIncome":192000000,"epsdiluted":0.38,"generalAndAdministrativeExpenses":172000000,"operatingIncomeRatio":0.12083071113908118,"costOfRevenue":251000000,"researchAndDevelopmentExpenses":356000000,"sellingAndMarketingExpenses":565000000}},{"period":"Q3","year":"2015","data":{"operatingIncomeRatio":0.2392933618843683,"sellingGeneralAndAdministrativeExpenses":809000000,"netIncomeRatio":0.20021413276231265,"researchAndDevelopmentExpenses":342000000,"epsdiluted":0.88,"operatingIncome":447000000,"grossProfitRatio":0.857066381156317,"totalOtherIncomeExpensesNet":6000000,"netIncome":374000000,"incomeTaxExpense":79000000,"otherExpenses":0,"grossProfit":1601000000,"eps":0.89,"weightedAverageShsOut":421640000,"generalAndAdministrativeExpenses":198000000,"weightedAverageShsOutDil":422858000,"revenue":1868000000,"incomeBeforeTax":453000000,"operatingExpenses":1151000000,"sellingAndMarketingExpenses":611000000,"costOfRevenue":267000000}},{"year":"2015","period":"Q2","data":{"totalOtherIncomeExpensesNet":-1000000,"sellingAndMarketingExpenses":556000000,"netIncome":256000000,"otherExpenses":0,"eps":0.61,"operatingIncomeRatio":0.19497607655502391,"sellingGeneralAndAdministrativeExpenses":757000000,"researchAndDevelopmentExpenses":331000000,"incomeTaxExpense":69000000,"weightedAverageShsOut":422329000,"netIncomeRatio":0.15311004784688995,"generalAndAdministrativeExpenses":201000000,"grossProfitRatio":0.8456937799043063,"epsdiluted":0.6,"weightedAverageShsOutDil":423981000,"operatingIncome":326000000,"incomeBeforeTax":325000000,"operatingExpenses":1088000000,"costOfRevenue":258000000,"revenue":1672000000,"grossProfit":1414000000}},{"year":"2015","period":"Q1","data":{"operatingIncomeRatio":0.13543721236028927,"sellingAndMarketingExpenses":565000000,"weightedAverageShsOutDil":426797000,"incomeBeforeTax":213000000,"operatingIncome":206000000,"totalOtherIncomeExpensesNet":7000000,"operatingExpenses":1067000000,"otherExpenses":0,"researchAndDevelopmentExpenses":322000000,"costOfRevenue":250000000,"netIncomeRatio":0.11308349769888232,"generalAndAdministrativeExpenses":180000000,"incomeTaxExpense":41000000,"epsdiluted":0.4,"grossProfit":1271000000,"revenue":1521000000,"sellingGeneralAndAdministrativeExpenses":745000000,"netIncome":172000000,"weightedAverageShsOut":424169000,"eps":0.41,"grossProfitRatio":0.8356344510190664}},{"data":{"incomeTaxExpense":26000000,"sellingAndMarketingExpenses":536000000,"netIncome":196000000,"totalOtherIncomeExpensesNet":4000000,"epsdiluted":0.45,"weightedAverageShsOut":427962000,"revenue":1511000000,"otherExpenses":0,"grossProfitRatio":0.8391793514228988,"sellingGeneralAndAdministrativeExpenses":723000000,"generalAndAdministrativeExpenses":187000000,"weightedAverageShsOutDil":430496000,"eps":0.46,"costOfRevenue":243000000,"operatingIncomeRatio":0.1442753143613501,"operatingIncome":218000000,"incomeBeforeTax":222000000,"operatingExpenses":1028000000,"netIncomeRatio":0.12971542025148908,"researchAndDevelopmentExpenses":305000000,"grossProfit":1268000000},"period":"Q4","year":"2015"},{"data":{"totalOtherIncomeExpensesNet":13000000,"netIncomeRatio":0.19153936545240893,"grossProfit":1447000000,"operatingIncomeRatio":0.20211515863689777,"weightedAverageShsOutDil":433205000,"epsdiluted":0.75,"operatingExpenses":1091000000,"netIncome":326000000,"incomeBeforeTax":357000000,"sellingAndMarketingExpenses":591000000,"weightedAverageShsOut":430198000,"researchAndDevelopmentExpenses":303000000,"sellingGeneralAndAdministrativeExpenses":788000000,"operatingIncome":344000000,"generalAndAdministrativeExpenses":197000000,"eps":0.76,"incomeTaxExpense":31000000,"otherExpenses":0,"costOfRevenue":255000000,"grossProfitRatio":0.8501762632197415,"revenue":1702000000},"period":"Q3","year":"2014"},{"period":"Q2","data":{"revenue":1515000000,"netIncomeRatio":0.12805280528052806,"researchAndDevelopmentExpenses":327000000,"epsdiluted":0.45,"netIncome":194000000,"weightedAverageShsOut":430463000,"incomeTaxExpense":50000000,"sellingAndMarketingExpenses":529000000,"eps":0.45,"costOfRevenue":242000000,"incomeBeforeTax":244000000,"weightedAverageShsOutDil":434118000,"totalOtherIncomeExpensesNet":2000000,"grossProfit":1273000000,"sellingGeneralAndAdministrativeExpenses":698000000,"generalAndAdministrativeExpenses":169000000,"operatingIncomeRatio":0.15973597359735975,"otherExpenses":0,"grossProfitRatio":0.8402640264026403,"operatingIncome":242000000,"operatingExpenses":1025000000},"year":"2014"},{"period":"Q1","data":{"sellingGeneralAndAdministrativeExpenses":723000000,"otherExpenses":0,"grossProfitRatio":0.8503774879890186,"costOfRevenue":218000000,"incomeBeforeTax":202000000,"weightedAverageShsOutDil":434199000,"operatingIncome":200000000,"researchAndDevelopmentExpenses":317000000,"netIncome":167000000,"incomeTaxExpense":35000000,"weightedAverageShsOut":430216000,"netIncomeRatio":0.11461908030199039,"revenue":1457000000,"generalAndAdministrativeExpenses":179000000,"grossProfit":1239000000,"epsdiluted":0.38,"totalOtherIncomeExpensesNet":2000000,"eps":0.39,"operatingIncomeRatio":0.13726835964310227,"sellingAndMarketingExpenses":544000000,"operatingExpenses":1040000000},"year":"2014"},{"period":"Q4","data":{"epsdiluted":0.46,"researchAndDevelopmentExpenses":293000000,"costOfRevenue":201000000,"eps":0.46,"incomeBeforeTax":245000000,"grossProfit":1159000000,"weightedAverageShsOutDil":434729000,"incomeTaxExpense":46000000,"otherExpenses":0,"operatingIncomeRatio":0.17720588235294119,"totalOtherIncomeExpensesNet":4000000,"grossProfitRatio":0.8522058823529411,"netIncomeRatio":0.1463235294117647,"sellingAndMarketingExpenses":474000000,"operatingExpenses":918000000,"netIncome":199000000,"generalAndAdministrativeExpenses":151000000,"sellingGeneralAndAdministrativeExpenses":625000000,"operatingIncome":241000000,"revenue":1360000000,"weightedAverageShsOut":430546000},"year":"2014"},{"data":{"otherExpenses":0,"incomeBeforeTax":381000000,"incomeTaxExpense":46000000,"operatingExpenses":913000000,"researchAndDevelopmentExpenses":285000000,"totalOtherIncomeExpensesNet":7000000,"weightedAverageShsOut":430174000,"sellingGeneralAndAdministrativeExpenses":628000000,"grossProfitRatio":0.8705327039784221,"netIncomeRatio":0.22589345920431558,"operatingIncomeRatio":0.2521915037086986,"epsdiluted":0.77,"weightedAverageShsOutDil":433621000,"eps":0.78,"revenue":1483000000,"costOfRevenue":192000000,"operatingIncome":374000000,"generalAndAdministrativeExpenses":121000000,"netIncome":335000000,"sellingAndMarketingExpenses":507000000,"grossProfit":1291000000},"year":"2013","period":"Q3"},{"year":"2013","period":"Q2","data":{"operatingIncomeRatio":0.22265321955003878,"epsdiluted":0.6,"totalOtherIncomeExpensesNet":21000000,"generalAndAdministrativeExpenses":103000000,"netIncomeRatio":0.20248254460822343,"weightedAverageShsOutDil":433000000,"sellingAndMarketingExpenses":449000000,"grossProfitRatio":0.8580294802172227,"otherExpenses":0,"netIncome":261000000,"weightedAverageShsOut":430000000,"eps":0.61,"operatingExpenses":818000000,"costOfRevenue":183000000,"grossProfit":1106000000,"researchAndDevelopmentExpenses":266000000,"sellingGeneralAndAdministrativeExpenses":552000000,"operatingIncome":287000000,"revenue":1289000000,"incomeTaxExpense":47000000,"incomeBeforeTax":308000000}},{"data":{"researchAndDevelopmentExpenses":260700000,"grossProfitRatio":0.860751347437857,"incomeBeforeTax":293300000,"sellingAndMarketingExpenses":442100000,"operatingIncomeRatio":0.2174402702920119,"grossProfit":1070000000,"operatingExpenses":799100000,"weightedAverageShsOut":428300000,"eps":0.57,"weightedAverageShsOutDil":432000000,"operatingIncome":270300000,"netIncome":244100000,"sellingGeneralAndAdministrativeExpenses":538400000,"epsdiluted":0.57,"otherExpenses":0,"generalAndAdministrativeExpenses":96300000,"incomeTaxExpense":49200000,"netIncomeRatio":0.19636392888745877,"totalOtherIncomeExpensesNet":23000000,"costOfRevenue":173100000,"revenue":1243100000},"period":"Q1","year":"2013"},{"period":"Q4","data":{"grossProfit":1009526000,"totalOtherIncomeExpensesNet":3881000,"epsdiluted":0.4,"researchAndDevelopmentExpenses":270558000,"revenue":1191466000,"weightedAverageShsOut":428005000,"grossProfitRatio":0.8472973630804403,"incomeTaxExpense":-9486000,"weightedAverageShsOutDil":432631000,"netIncome":173569000,"operatingIncome":160202000,"eps":0.41,"netIncomeRatio":0.1456768384494396,"operatingExpenses":786442000,"costOfRevenue":181940000,"operatingIncomeRatio":0.13445788633498565,"sellingGeneralAndAdministrativeExpenses":515884000,"generalAndAdministrativeExpenses":98466000,"otherExpenses":0,"sellingAndMarketingExpenses":417418000,"incomeBeforeTax":164083000},"year":"2013"},{"year":"2012","data":{"eps":0.48,"operatingIncomeRatio":0.19527821490849898,"costOfRevenue":191824000,"researchAndDevelopmentExpenses":268323000,"otherExpenses":0,"incomeBeforeTax":259924000,"revenue":1293155000,"operatingExpenses":848806000,"grossProfitRatio":0.8516620204074531,"grossProfit":1101331000,"sellingAndMarketingExpenses":478401000,"totalOtherIncomeExpensesNet":7399000,"generalAndAdministrativeExpenses":102082000,"netIncomeRatio":0.15912168301557045,"sellingGeneralAndAdministrativeExpenses":580483000,"weightedAverageShsOutDil":433205000,"netIncome":205769000,"incomeTaxExpense":54155000,"weightedAverageShsOut":427266000,"epsdiluted":0.47,"operatingIncome":252525000},"period":"Q3"},{"data":{"grossProfitRatio":0.8417883643061029,"weightedAverageShsOutDil":433288000,"incomeBeforeTax":195147000,"weightedAverageShsOut":427142000,"netIncome":156768000,"grossProfit":954322000,"eps":0.37,"costOfRevenue":179362000,"totalOtherIncomeExpensesNet":4804000,"operatingExpenses":763979000,"epsdiluted":0.36,"incomeTaxExpense":38379000,"sellingAndMarketingExpenses":411535000,"netIncomeRatio":0.13828191982951157,"generalAndAdministrativeExpenses":92537000,"sellingGeneralAndAdministrativeExpenses":504072000,"revenue":1133684000,"otherExpenses":0,"researchAndDevelopmentExpenses":259907000,"operatingIncomeRatio":0.16789775634127324,"operatingIncome":190343000},"year":"2012","period":"Q2"},{"period":"Q1","data":{"netIncome":191729000,"researchAndDevelopmentExpenses":248594000,"totalOtherIncomeExpensesNet":2227000,"otherExpenses":0,"operatingIncome":211910000,"eps":0.45,"weightedAverageShsOut":427223000,"sellingAndMarketingExpenses":391501000,"incomeBeforeTax":214137000,"operatingExpenses":731894000,"grossProfitRatio":0.8404115309885969,"incomeTaxExpense":22408000,"generalAndAdministrativeExpenses":91799000,"costOfRevenue":179222000,"epsdiluted":0.44,"weightedAverageShsOutDil":434647000,"revenue":1123026000,"sellingGeneralAndAdministrativeExpenses":483300000,"operatingIncomeRatio":0.1886955422225309,"grossProfit":943804000,"netIncomeRatio":0.17072534384778268},"year":"2012"},{"data":{"eps":0.45,"grossProfitRatio":0.8380232035800459,"epsdiluted":0.44,"incomeTaxExpense":32470000,"revenue":1055182000,"sellingGeneralAndAdministrativeExpenses":444712000,"costOfRevenue":170915000,"generalAndAdministrativeExpenses":81300000,"sellingAndMarketingExpenses":363412000,"operatingExpenses":667102000,"operatingIncomeRatio":0.20580809756042084,"grossProfit":884267000,"incomeBeforeTax":223906000,"netIncomeRatio":0.18142462627300315,"netIncome":191436000,"totalOtherIncomeExpensesNet":6741000,"otherExpenses":0,"operatingIncome":217165000,"weightedAverageShsOutDil":433213000,"researchAndDevelopmentExpenses":222390000,"weightedAverageShsOut":424989000},"period":"Q4","year":"2012"},{"period":"Q3","year":"2011","data":{"operatingIncomeRatio":0.20188210528698428,"sellingGeneralAndAdministrativeExpenses":462380000,"costOfRevenue":166874000,"operatingIncome":214056000,"incomeBeforeTax":208866000,"generalAndAdministrativeExpenses":77144000,"sellingAndMarketingExpenses":385236000,"netIncome":200428000,"weightedAverageShsOut":424989000,"researchAndDevelopmentExpenses":216992000,"revenue":1060302000,"netIncomeRatio":0.1890291633892985,"grossProfit":893428000,"eps":0.47,"incomeTaxExpense":8438000,"totalOtherIncomeExpensesNet":-5190000,"weightedAverageShsOutDil":433213000,"operatingExpenses":679372000,"otherExpenses":0,"grossProfitRatio":0.8426165375525086,"epsdiluted":0.46}},{"data":{"sellingAndMarketingExpenses":331626000,"sellingGeneralAndAdministrativeExpenses":408746000,"epsdiluted":0.41,"operatingIncomeRatio":0.1918761008766668,"researchAndDevelopmentExpenses":199655000,"weightedAverageShsOut":422030000,"incomeTaxExpense":5621000,"totalOtherIncomeExpensesNet":2438000,"operatingExpenses":608401000,"netIncome":177538000,"operatingIncome":180721000,"incomeBeforeTax":183159000,"grossProfitRatio":0.8378309796647708,"weightedAverageShsOutDil":431881000,"revenue":941863000,"eps":0.42,"generalAndAdministrativeExpenses":77120000,"grossProfit":789122000,"costOfRevenue":152741000,"netIncomeRatio":0.18849662849055543,"otherExpenses":0},"period":"Q2","year":"2011"},{"year":"2011","period":"Q1","data":{"operatingExpenses":581843000,"operatingIncomeRatio":0.20287665136071037,"otherExpenses":0,"researchAndDevelopmentExpenses":189241000,"weightedAverageShsOutDil":430473000,"generalAndAdministrativeExpenses":78042000,"grossProfit":768735000,"epsdiluted":0.51,"sellingGeneralAndAdministrativeExpenses":392602000,"incomeBeforeTax":246274000,"revenue":921210000,"netIncome":220158000,"weightedAverageShsOut":419657000,"operatingIncome":186892000,"eps":0.52,"totalOtherIncomeExpensesNet":59382000,"grossProfitRatio":0.8344839938776175,"incomeTaxExpense":26116000,"costOfRevenue":152475000,"sellingAndMarketingExpenses":314560000,"netIncomeRatio":0.2389878529325561}},{"year":"2011","data":{"netIncome":125812000,"otherExpenses":0,"totalOtherIncomeExpensesNet":2612000,"operatingIncome":153502000,"sellingGeneralAndAdministrativeExpenses":371159000,"epsdiluted":0.29,"incomeTaxExpense":30302000,"eps":0.3,"operatingIncomeRatio":0.1819345494541442,"costOfRevenue":149897000,"weightedAverageShsOutDil":429247000,"sellingAndMarketingExpenses":302924000,"weightedAverageShsOut":417444000,"revenue":843721000,"netIncomeRatio":0.14911564367841976,"grossProfit":693824000,"researchAndDevelopmentExpenses":169163000,"incomeBeforeTax":156114000,"grossProfitRatio":0.8223381899940857,"generalAndAdministrativeExpenses":68235000,"operatingExpenses":540322000},"period":"Q4"},{"data":{"weightedAverageShsOut":417444000,"netIncome":119880000,"operatingIncomeRatio":0.15630022221929707,"otherExpenses":0,"operatingIncome":130614000,"incomeTaxExpense":5167000,"researchAndDevelopmentExpenses":177671000,"generalAndAdministrativeExpenses":73980000,"sellingAndMarketingExpenses":313045000,"epsdiluted":0.28,"totalOtherIncomeExpensesNet":-5567000,"costOfRevenue":140351000,"revenue":835661000,"operatingExpenses":564696000,"eps":0.29,"grossProfitRatio":0.832047923739411,"sellingGeneralAndAdministrativeExpenses":387025000,"grossProfit":695310000,"netIncomeRatio":0.14345530065421266,"incomeBeforeTax":125047000,"weightedAverageShsOutDil":429247000},"period":"Q3","year":"2010"},{"year":"2010","period":"Q2","data":{"operatingIncomeRatio":0.13162430258524735,"epsdiluted":0.2,"costOfRevenue":126562000,"netIncomeRatio":0.1184467514648335,"eps":0.21,"operatingIncome":94012000,"totalOtherIncomeExpensesNet":2733000,"researchAndDevelopmentExpenses":175429000,"operatingExpenses":493671000,"weightedAverageShsOut":411755000,"grossProfitRatio":0.8228030997766873,"sellingGeneralAndAdministrativeExpenses":318242000,"incomeBeforeTax":96745000,"weightedAverageShsOutDil":426581000,"generalAndAdministrativeExpenses":66497000,"sellingAndMarketingExpenses":251745000,"revenue":714245000,"otherExpenses":0,"netIncome":84600000,"grossProfit":587683000,"incomeTaxExpense":12145000}},{"data":{"epsdiluted":0.18,"incomeTaxExpense":22406000,"incomeBeforeTax":96944000,"operatingIncomeRatio":0.15014156319000926,"weightedAverageShsOutDil":422333000,"generalAndAdministrativeExpenses":61153000,"sellingAndMarketingExpenses":231662000,"totalOtherIncomeExpensesNet":-4237000,"operatingExpenses":454571000,"researchAndDevelopmentExpenses":161756000,"operatingIncome":101181000,"eps":0.18,"netIncomeRatio":0.11060625845817802,"grossProfitRatio":0.8246753246753247,"costOfRevenue":118152000,"sellingGeneralAndAdministrativeExpenses":292815000,"otherExpenses":0,"grossProfit":555752000,"weightedAverageShsOut":407931000,"netIncome":74538000,"revenue":673904000},"period":"Q1","year":"2010"},{"period":"Q4","year":"2010","data":{"researchAndDevelopmentExpenses":138112000,"weightedAverageShsOut":404480000,"revenue":633533000,"costOfRevenue":108650000,"sellingAndMarketingExpenses":216829000,"generalAndAdministrativeExpenses":67756000,"netIncomeRatio":0.12378360716805596,"operatingExpenses":422697000,"grossProfitRatio":0.8285014356000397,"incomeBeforeTax":97639000,"eps":0.19,"otherExpenses":0,"sellingGeneralAndAdministrativeExpenses":284585000,"grossProfit":524883000,"netIncome":78421000,"operatingIncome":102186000,"epsdiluted":0.19,"weightedAverageShsOutDil":416853000,"totalOtherIncomeExpensesNet":-4547000,"operatingIncomeRatio":0.16129546527173802,"incomeTaxExpense":19218000}},{"data":{"incomeTaxExpense":10828000,"otherExpenses":0,"costOfRevenue":107506000,"grossProfitRatio":0.8232393567258193,"operatingIncomeRatio":0.1169958615655022,"generalAndAdministrativeExpenses":63680000,"epsdiluted":0.14,"totalOtherIncomeExpensesNet":-3920000,"netIncome":56409000,"sellingAndMarketingExpenses":229596000,"operatingExpenses":429538000,"weightedAverageShsOutDil":416853000,"eps":0.14,"incomeBeforeTax":67237000,"grossProfit":500695000,"weightedAverageShsOut":404480000,"revenue":608201000,"operatingIncome":71157000,"sellingGeneralAndAdministrativeExpenses":293276000,"researchAndDevelopmentExpenses":136262000,"netIncomeRatio":0.09274729900148142},"period":"Q3","year":"2009"},{"data":{"researchAndDevelopmentExpenses":133509000,"epsdiluted":0.09,"generalAndAdministrativeExpenses":51711000,"netIncomeRatio":0.07803761503294532,"grossProfitRatio":0.8038329681817903,"weightedAverageShsOut":396366000,"operatingIncome":23236000,"eps":0.1,"sellingGeneralAndAdministrativeExpenses":236933000,"weightedAverageShsOutDil":402888000,"sellingAndMarketingExpenses":185222000,"grossProfit":393678000,"otherExpenses":0,"totalOtherIncomeExpensesNet":8638000,"revenue":489751000,"incomeTaxExpense":-6345000,"operatingExpenses":370442000,"costOfRevenue":96073000,"incomeBeforeTax":31874000,"netIncome":38219000,"operatingIncomeRatio":0.04744451772431297},"year":"2009","period":"Q2"},{"data":{"weightedAverageShsOut":391841000,"revenue":455675000,"grossProfitRatio":0.8219213255061173,"otherExpenses":0,"researchAndDevelopmentExpenses":121380000,"generalAndAdministrativeExpenses":47729000,"costOfRevenue":81146000,"sellingGeneralAndAdministrativeExpenses":215150000,"operatingIncome":37999000,"netIncome":32535000,"incomeTaxExpense":6336000,"epsdiluted":0.08,"sellingAndMarketingExpenses":167421000,"incomeBeforeTax":38871000,"weightedAverageShsOutDil":395826000,"grossProfit":374529000,"operatingExpenses":336530000,"netIncomeRatio":0.0713995720634224,"operatingIncomeRatio":0.08339057442255994,"totalOtherIncomeExpensesNet":872000,"eps":0.08},"period":"Q1","year":"2009"},{"period":"Q4","data":{"weightedAverageShsOutDil":391111000,"netIncomeRatio":0.1486997937530565,"generalAndAdministrativeExpenses":48859000,"operatingIncome":86903000,"netIncome":69935000,"incomeTaxExpense":15532000,"grossProfit":395307000,"epsdiluted":0.18,"revenue":470310000,"totalOtherIncomeExpensesNet":-1436000,"otherExpenses":0,"sellingAndMarketingExpenses":154144000,"operatingExpenses":308404000,"operatingIncomeRatio":0.18477812506644553,"weightedAverageShsOut":389857000,"costOfRevenue":75003000,"researchAndDevelopmentExpenses":105401000,"sellingGeneralAndAdministrativeExpenses":203003000,"grossProfitRatio":0.8405243350130764,"eps":0.18,"incomeBeforeTax":85467000},"year":"2009"},{"period":"Q3","data":{"otherExpenses":0,"epsdiluted":0.28,"weightedAverageShsOut":389857000,"operatingExpenses":340539000,"costOfRevenue":71950000,"incomeTaxExpense":-10830000,"weightedAverageShsOutDil":391111000,"netIncome":111454000,"researchAndDevelopmentExpenses":110506000,"totalOtherIncomeExpensesNet":-1490000,"netIncomeRatio":0.21658249174606445,"eps":0.29,"grossProfitRatio":0.8601834812467086,"sellingAndMarketingExpenses":0,"incomeBeforeTax":100624000,"grossProfit":442653000,"revenue":514603000,"operatingIncome":102114000,"sellingGeneralAndAdministrativeExpenses":230033000,"operatingIncomeRatio":0.19843257812333,"generalAndAdministrativeExpenses":0},"year":"2008"},{"data":{"operatingIncome":101020000,"totalOtherIncomeExpensesNet":2510000,"netIncomeRatio":0.17641240275268416,"operatingExpenses":296647000,"grossProfit":397667000,"sellingAndMarketingExpenses":0,"incomeTaxExpense":20242000,"weightedAverageShsOutDil":394232000,"weightedAverageShsOut":387621000,"researchAndDevelopmentExpenses":85315000,"revenue":472121000,"sellingGeneralAndAdministrativeExpenses":211332000,"costOfRevenue":74454000,"grossProfitRatio":0.8422989021882102,"epsdiluted":0.21,"generalAndAdministrativeExpenses":0,"eps":0.21,"incomeBeforeTax":103530000,"otherExpenses":0,"operatingIncomeRatio":0.21397057110359421,"netIncome":83288000},"year":"2008","period":"Q2"},{"data":{"totalOtherIncomeExpensesNet":3101000,"otherExpenses":0,"netIncomeRatio":0.11473972218324681,"incomeBeforeTax":64101000,"generalAndAdministrativeExpenses":0,"sellingGeneralAndAdministrativeExpenses":200469000,"operatingIncomeRatio":0.1337343903465694,"grossProfit":375597000,"sellingAndMarketingExpenses":0,"weightedAverageShsOutDil":398979000,"costOfRevenue":80531000,"eps":0.14,"researchAndDevelopmentExpenses":114128000,"weightedAverageShsOut":382931000,"netIncome":52336000,"revenue":456128000,"operatingIncome":61000000,"incomeTaxExpense":11765000,"epsdiluted":0.13,"grossProfitRatio":0.823446488704925,"operatingExpenses":314597000},"period":"Q1","year":"2008"},{"year":"2008","period":"Q4","data":{"eps":0.11,"weightedAverageShsOutDil":398063000,"epsdiluted":0.11,"grossProfitRatio":0.8238831517087921,"netIncome":43055000,"incomeBeforeTax":51030000,"operatingExpenses":312614000,"sellingGeneralAndAdministrativeExpenses":193359000,"researchAndDevelopmentExpenses":119255000,"totalOtherIncomeExpensesNet":2639000,"otherExpenses":0,"incomeTaxExpense":7975000,"grossProfit":361005000,"netIncomeRatio":0.09825982769441433,"sellingAndMarketingExpenses":0,"operatingIncomeRatio":0.11043761054373252,"generalAndAdministrativeExpenses":0,"weightedAverageShsOut":381026000,"costOfRevenue":77170000,"revenue":438175000,"operatingIncome":48391000}},{"data":{"netIncomeRatio":0.18947815019092065,"sellingAndMarketingExpenses":0,"eps":0.21,"generalAndAdministrativeExpenses":0,"researchAndDevelopmentExpenses":91562000,"weightedAverageShsOut":381026000,"incomeBeforeTax":83260000,"weightedAverageShsOutDil":398063000,"operatingIncome":76474000,"grossProfit":345293000,"epsdiluted":0.2,"operatingExpenses":268819000,"grossProfitRatio":0.8371246742226801,"sellingGeneralAndAdministrativeExpenses":177257000,"totalOtherIncomeExpensesNet":6786000,"operatingIncomeRatio":0.1854027516819201,"costOfRevenue":67182000,"netIncome":78155000,"revenue":412475000,"incomeTaxExpense":5105000,"otherExpenses":0},"year":"2007","period":"Q3"},{"period":"Q2","year":"2007","data":{"incomeBeforeTax":66288000,"netIncome":64678000,"operatingExpenses":233415000,"sellingGeneralAndAdministrativeExpenses":165575000,"epsdiluted":0.18,"generalAndAdministrativeExpenses":0,"operatingIncome":65750000,"otherExpenses":0,"eps":0.18,"sellingAndMarketingExpenses":0,"operatingIncomeRatio":0.18375366109955954,"totalOtherIncomeExpensesNet":538000,"weightedAverageShsOut":356431000,"revenue":357816000,"weightedAverageShsOutDil":368567000,"grossProfit":299165000,"incomeTaxExpense":1610000,"researchAndDevelopmentExpenses":67840000,"costOfRevenue":58651000,"netIncomeRatio":0.18075770787220247,"grossProfitRatio":0.8360861448342165}},{"period":"Q1","year":"2007","data":{"weightedAverageShsOut":332500000,"netIncomeRatio":0.11530026109660574,"otherExpenses":0,"operatingExpenses":201273000,"epsdiluted":0.1,"sellingGeneralAndAdministrativeExpenses":129692000,"grossProfit":248008000,"sellingAndMarketingExpenses":0,"netIncome":34224000,"operatingIncome":46735000,"costOfRevenue":48817000,"incomeBeforeTax":41512000,"operatingIncomeRatio":0.1574496757348606,"generalAndAdministrativeExpenses":0,"eps":0.1,"weightedAverageShsOutDil":332501000,"grossProfitRatio":0.8355360902888908,"totalOtherIncomeExpensesNet":-5223000,"incomeTaxExpense":7288000,"revenue":296825000,"researchAndDevelopmentExpenses":71581000}},{"period":"Q4","data":{"revenue":258695000,"costOfRevenue":44024000,"weightedAverageShsOutDil":332500000,"netIncomeRatio":0.1587970389841319,"grossProfit":214671000,"incomeBeforeTax":49418000,"operatingIncomeRatio":0.17929221670306733,"weightedAverageShsOut":332500000,"netIncome":41080000,"generalAndAdministrativeExpenses":0,"totalOtherIncomeExpensesNet":3036000,"sellingAndMarketingExpenses":0,"otherExpenses":0,"eps":0.12,"researchAndDevelopmentExpenses":54958000,"operatingExpenses":168289000,"grossProfitRatio":0.8298227642590695,"epsdiluted":0.12,"incomeTaxExpense":8338000,"operatingIncome":46382000,"sellingGeneralAndAdministrativeExpenses":113331000},"year":"2007"},{"year":"2006","data":{"revenue":191609000,"incomeTaxExpense":0,"epsdiluted":0.066,"weightedAverageShsOut":332500000,"sellingAndMarketingExpenses":0,"grossProfitRatio":0,"costOfRevenue":0,"incomeBeforeTax":0,"researchAndDevelopmentExpenses":0,"generalAndAdministrativeExpenses":0,"operatingIncomeRatio":-2.0247274397340416,"netIncome":21793000,"totalOtherIncomeExpensesNet":0,"eps":0.066,"netIncomeRatio":0.11373682864583605,"grossProfit":0,"otherExpenses":0,"operatingExpenses":0,"sellingGeneralAndAdministrativeExpenses":0,"operatingIncome":-387956000,"weightedAverageShsOutDil":332500000},"period":"Q3"},{"period":"Q2","data":{"netIncome":21793000,"revenue":191609000,"researchAndDevelopmentExpenses":0,"grossProfitRatio":0,"epsdiluted":0.0667,"operatingIncome":191609000,"costOfRevenue":0,"generalAndAdministrativeExpenses":0,"incomeTaxExpense":0,"totalOtherIncomeExpensesNet":0,"incomeBeforeTax":0,"sellingGeneralAndAdministrativeExpenses":0,"sellingAndMarketingExpenses":0,"grossProfit":0,"eps":0.0667,"operatingIncomeRatio":1,"otherExpenses":0,"netIncomeRatio":0.11373682864583605,"weightedAverageShsOutDil":332500000,"operatingExpenses":0,"weightedAverageShsOut":332500000},"year":"2006"},{"period":"Q1","year":"2006","data":{"researchAndDevelopmentExpenses":0,"operatingIncome":191609000,"operatingIncomeRatio":1,"weightedAverageShsOutDil":332500000,"totalOtherIncomeExpensesNet":0,"eps":0.0667,"grossProfit":0,"sellingAndMarketingExpenses":0,"sellingGeneralAndAdministrativeExpenses":0,"netIncomeRatio":0.11373682864583605,"epsdiluted":0.0667,"incomeBeforeTax":0,"operatingExpenses":0,"weightedAverageShsOut":332500000,"otherExpenses":0,"revenue":191609000,"incomeTaxExpense":0,"costOfRevenue":0,"netIncome":21793000,"grossProfitRatio":0,"generalAndAdministrativeExpenses":0}},{"data":{"netIncome":20511000,"weightedAverageShsOut":332500000,"weightedAverageShsOutDil":332500000,"eps":0.06,"epsdiluted":0.06,"incomeBeforeTax":0,"incomeTaxExpense":0,"revenue":129077000,"grossProfit":0,"otherExpenses":0,"grossProfitRatio":0,"sellingGeneralAndAdministrativeExpenses":0,"researchAndDevelopmentExpenses":0,"generalAndAdministrativeExpenses":0,"costOfRevenue":0,"sellingAndMarketingExpenses":0,"operatingExpenses":0,"operatingIncome":129077000,"netIncomeRatio":0.15890514963936256,"totalOtherIncomeExpensesNet":0,"operatingIncomeRatio":1},"period":"Q4","year":"2006"},{"year":"2005","period":"Q3","data":{"costOfRevenue":0,"otherExpenses":0,"operatingIncome":-196711000,"netIncome":16694000,"sellingAndMarketingExpenses":0,"weightedAverageShsOut":332500000,"incomeTaxExpense":0,"weightedAverageShsOutDil":332500000,"totalOtherIncomeExpensesNet":0,"epsdiluted":0.05,"generalAndAdministrativeExpenses":0,"grossProfit":0,"eps":0.05,"grossProfitRatio":0,"operatingIncomeRatio":-2.032810433201058,"sellingGeneralAndAdministrativeExpenses":0,"netIncomeRatio":0.17251570767195767,"revenue":96768000,"operatingExpenses":0,"researchAndDevelopmentExpenses":0,"incomeBeforeTax":0}},{"period":"Q2","year":"2005","data":{"revenue":96769000,"netIncome":16694000,"operatingIncome":96769000,"operatingExpenses":0,"totalOtherIncomeExpensesNet":0,"operatingIncomeRatio":1,"grossProfitRatio":0,"generalAndAdministrativeExpenses":0,"weightedAverageShsOutDil":332500000,"eps":0.05,"sellingAndMarketingExpenses":0,"netIncomeRatio":0.17251392491397038,"otherExpenses":0,"costOfRevenue":0,"incomeBeforeTax":0,"weightedAverageShsOut":332500000,"incomeTaxExpense":0,"researchAndDevelopmentExpenses":0,"sellingGeneralAndAdministrativeExpenses":0,"grossProfit":0,"epsdiluted":0.05}},{"data":{"weightedAverageShsOut":332500000,"sellingAndMarketingExpenses":0,"operatingIncome":96769000,"costOfRevenue":0,"eps":0.05,"sellingGeneralAndAdministrativeExpenses":0,"incomeTaxExpense":0,"grossProfit":0,"incomeBeforeTax":0,"weightedAverageShsOutDil":332500000,"netIncomeRatio":0.17251392491397038,"grossProfitRatio":0,"researchAndDevelopmentExpenses":0,"generalAndAdministrativeExpenses":0,"epsdiluted":0.05,"totalOtherIncomeExpensesNet":0,"revenue":96769000,"netIncome":16694000,"operatingExpenses":0,"otherExpenses":0,"operatingIncomeRatio":1},"year":"2005","period":"Q1"},{"period":"Q4","year":"2005","data":{"sellingGeneralAndAdministrativeExpenses":0,"operatingExpenses":0,"incomeBeforeTax":0,"grossProfit":0,"sellingAndMarketingExpenses":0,"totalOtherIncomeExpensesNet":0,"researchAndDevelopmentExpenses":0,"incomeTaxExpense":0,"netIncome":16694000,"epsdiluted":0.05,"revenue":96769000,"operatingIncome":96769000,"netIncomeRatio":0.17251392491397038,"generalAndAdministrativeExpenses":0,"eps":0.05,"weightedAverageShsOut":332500000,"costOfRevenue":0,"operatingIncomeRatio":1,"otherExpenses":0,"weightedAverageShsOutDil":332500000,"grossProfitRatio":0}}]},"__N_SSG":true},"page":"/quote/[symbol]/income-statement","query":{"symbol":"VMW"},"buildId":"Njk4sJo_1dBWR55wHuASm","isFallback":false,"gsp":true,"scriptLoader":[]}